<?xml version="1.0" encoding="UTF-8"?>
<?xml-stylesheet href="CoreNLP-to-HTML.xsl" type="text/xsl"?>
<root>
  <document>
    <sentences>
      <sentence id="1">
        <tokens>
          <token id="1">
            <word>I</word>
            <lemma>I</lemma>
            <CharacterOffsetBegin>0</CharacterOffsetBegin>
            <CharacterOffsetEnd>1</CharacterOffsetEnd>
            <POS>PRP</POS>
          </token>
          <token id="2">
            <word>was</word>
            <lemma>be</lemma>
            <CharacterOffsetBegin>2</CharacterOffsetBegin>
            <CharacterOffsetEnd>5</CharacterOffsetEnd>
            <POS>VBD</POS>
          </token>
          <token id="3">
            <word>making</word>
            <lemma>make</lemma>
            <CharacterOffsetBegin>6</CharacterOffsetBegin>
            <CharacterOffsetEnd>12</CharacterOffsetEnd>
            <POS>VBG</POS>
          </token>
          <token id="4">
            <word>a</word>
            <lemma>a</lemma>
            <CharacterOffsetBegin>13</CharacterOffsetBegin>
            <CharacterOffsetEnd>14</CharacterOffsetEnd>
            <POS>DT</POS>
          </token>
          <token id="5">
            <word>cake</word>
            <lemma>cake</lemma>
            <CharacterOffsetBegin>15</CharacterOffsetBegin>
            <CharacterOffsetEnd>19</CharacterOffsetEnd>
            <POS>NN</POS>
          </token>
          <token id="6">
            <word>but</word>
            <lemma>but</lemma>
            <CharacterOffsetBegin>20</CharacterOffsetBegin>
            <CharacterOffsetEnd>23</CharacterOffsetEnd>
            <POS>CC</POS>
          </token>
          <token id="7">
            <word>when</word>
            <lemma>when</lemma>
            <CharacterOffsetBegin>24</CharacterOffsetBegin>
            <CharacterOffsetEnd>28</CharacterOffsetEnd>
            <POS>WRB</POS>
          </token>
          <token id="8">
            <word>I</word>
            <lemma>I</lemma>
            <CharacterOffsetBegin>29</CharacterOffsetBegin>
            <CharacterOffsetEnd>30</CharacterOffsetEnd>
            <POS>PRP</POS>
          </token>
          <token id="9">
            <word>added</word>
            <lemma>add</lemma>
            <CharacterOffsetBegin>31</CharacterOffsetBegin>
            <CharacterOffsetEnd>36</CharacterOffsetEnd>
            <POS>VBD</POS>
          </token>
          <token id="10">
            <word>too</word>
            <lemma>too</lemma>
            <CharacterOffsetBegin>37</CharacterOffsetBegin>
            <CharacterOffsetEnd>40</CharacterOffsetEnd>
            <POS>RB</POS>
          </token>
          <token id="11">
            <word>much</word>
            <lemma>much</lemma>
            <CharacterOffsetBegin>41</CharacterOffsetBegin>
            <CharacterOffsetEnd>45</CharacterOffsetEnd>
            <POS>JJ</POS>
          </token>
          <token id="12">
            <word>sugar</word>
            <lemma>sugar</lemma>
            <CharacterOffsetBegin>46</CharacterOffsetBegin>
            <CharacterOffsetEnd>51</CharacterOffsetEnd>
            <POS>NN</POS>
          </token>
          <token id="13">
            <word>,</word>
            <lemma>,</lemma>
            <CharacterOffsetBegin>51</CharacterOffsetBegin>
            <CharacterOffsetEnd>52</CharacterOffsetEnd>
            <POS>,</POS>
          </token>
          <token id="14">
            <word>it</word>
            <lemma>it</lemma>
            <CharacterOffsetBegin>53</CharacterOffsetBegin>
            <CharacterOffsetEnd>55</CharacterOffsetEnd>
            <POS>PRP</POS>
          </token>
          <token id="15">
            <word>became</word>
            <lemma>become</lemma>
            <CharacterOffsetBegin>56</CharacterOffsetBegin>
            <CharacterOffsetEnd>62</CharacterOffsetEnd>
            <POS>VBD</POS>
          </token>
          <token id="16">
            <word>the</word>
            <lemma>the</lemma>
            <CharacterOffsetBegin>63</CharacterOffsetBegin>
            <CharacterOffsetEnd>66</CharacterOffsetEnd>
            <POS>DT</POS>
          </token>
          <token id="17">
            <word>balls-up</word>
            <lemma>balls-up</lemma>
            <CharacterOffsetBegin>67</CharacterOffsetBegin>
            <CharacterOffsetEnd>75</CharacterOffsetEnd>
            <POS>NN</POS>
          </token>
          <token id="18">
            <word>of</word>
            <lemma>of</lemma>
            <CharacterOffsetBegin>76</CharacterOffsetBegin>
            <CharacterOffsetEnd>78</CharacterOffsetEnd>
            <POS>IN</POS>
          </token>
          <token id="19">
            <word>my</word>
            <lemma>my</lemma>
            <CharacterOffsetBegin>79</CharacterOffsetBegin>
            <CharacterOffsetEnd>81</CharacterOffsetEnd>
            <POS>PRP$</POS>
          </token>
          <token id="20">
            <word>cooking</word>
            <lemma>cooking</lemma>
            <CharacterOffsetBegin>82</CharacterOffsetBegin>
            <CharacterOffsetEnd>89</CharacterOffsetEnd>
            <POS>NN</POS>
          </token>
          <token id="21">
            <word>career</word>
            <lemma>career</lemma>
            <CharacterOffsetBegin>90</CharacterOffsetBegin>
            <CharacterOffsetEnd>96</CharacterOffsetEnd>
            <POS>NN</POS>
          </token>
          <token id="22">
            <word>.</word>
            <lemma>.</lemma>
            <CharacterOffsetBegin>96</CharacterOffsetBegin>
            <CharacterOffsetEnd>97</CharacterOffsetEnd>
            <POS>.</POS>
          </token>
        </tokens>
        <parse>(ROOT (S (S (NP (PRP I)) (VP (VBD was) (VP (VBG making) (NP (DT a) (NN cake))))) (CC but) (S (SBAR (WHADVP (WRB when)) (S (NP (PRP I)) (VP (VBD added) (NP (ADJP (RB too) (JJ much)) (NN sugar))))) (, ,) (NP (PRP it)) (VP (VBD became) (NP (NP (DT the) (NN balls-up)) (PP (IN of) (NP (PRP$ my) (NN cooking) (NN career)))))) (. .))) </parse>
        <dependencies type="basic-dependencies">
          <dep type="root">
            <governor idx="0">ROOT</governor>
            <dependent idx="3">making</dependent>
          </dep>
          <dep type="nsubj">
            <governor idx="3">making</governor>
            <dependent idx="1">I</dependent>
          </dep>
          <dep type="aux">
            <governor idx="3">making</governor>
            <dependent idx="2">was</dependent>
          </dep>
          <dep type="det">
            <governor idx="5">cake</governor>
            <dependent idx="4">a</dependent>
          </dep>
          <dep type="dobj">
            <governor idx="3">making</governor>
            <dependent idx="5">cake</dependent>
          </dep>
          <dep type="cc">
            <governor idx="3">making</governor>
            <dependent idx="6">but</dependent>
          </dep>
          <dep type="advmod">
            <governor idx="9">added</governor>
            <dependent idx="7">when</dependent>
          </dep>
          <dep type="nsubj">
            <governor idx="9">added</governor>
            <dependent idx="8">I</dependent>
          </dep>
          <dep type="advcl">
            <governor idx="17">balls-up</governor>
            <dependent idx="9">added</dependent>
          </dep>
          <dep type="advmod">
            <governor idx="11">much</governor>
            <dependent idx="10">too</dependent>
          </dep>
          <dep type="amod">
            <governor idx="12">sugar</governor>
            <dependent idx="11">much</dependent>
          </dep>
          <dep type="dobj">
            <governor idx="9">added</governor>
            <dependent idx="12">sugar</dependent>
          </dep>
          <dep type="nsubj">
            <governor idx="17">balls-up</governor>
            <dependent idx="14">it</dependent>
          </dep>
          <dep type="cop">
            <governor idx="17">balls-up</governor>
            <dependent idx="15">became</dependent>
          </dep>
          <dep type="det">
            <governor idx="17">balls-up</governor>
            <dependent idx="16">the</dependent>
          </dep>
          <dep type="conj">
            <governor idx="3">making</governor>
            <dependent idx="17">balls-up</dependent>
          </dep>
          <dep type="prep">
            <governor idx="17">balls-up</governor>
            <dependent idx="18">of</dependent>
          </dep>
          <dep type="poss">
            <governor idx="21">career</governor>
            <dependent idx="19">my</dependent>
          </dep>
          <dep type="nn">
            <governor idx="21">career</governor>
            <dependent idx="20">cooking</dependent>
          </dep>
          <dep type="pobj">
            <governor idx="18">of</governor>
            <dependent idx="21">career</dependent>
          </dep>
        </dependencies>
        <dependencies type="collapsed-dependencies">
          <dep type="root">
            <governor idx="0">ROOT</governor>
            <dependent idx="3">making</dependent>
          </dep>
          <dep type="nsubj">
            <governor idx="3">making</governor>
            <dependent idx="1">I</dependent>
          </dep>
          <dep type="aux">
            <governor idx="3">making</governor>
            <dependent idx="2">was</dependent>
          </dep>
          <dep type="det">
            <governor idx="5">cake</governor>
            <dependent idx="4">a</dependent>
          </dep>
          <dep type="dobj">
            <governor idx="3">making</governor>
            <dependent idx="5">cake</dependent>
          </dep>
          <dep type="advmod">
            <governor idx="9">added</governor>
            <dependent idx="7">when</dependent>
          </dep>
          <dep type="nsubj">
            <governor idx="9">added</governor>
            <dependent idx="8">I</dependent>
          </dep>
          <dep type="advcl">
            <governor idx="17">balls-up</governor>
            <dependent idx="9">added</dependent>
          </dep>
          <dep type="advmod">
            <governor idx="11">much</governor>
            <dependent idx="10">too</dependent>
          </dep>
          <dep type="amod">
            <governor idx="12">sugar</governor>
            <dependent idx="11">much</dependent>
          </dep>
          <dep type="dobj">
            <governor idx="9">added</governor>
            <dependent idx="12">sugar</dependent>
          </dep>
          <dep type="nsubj">
            <governor idx="17">balls-up</governor>
            <dependent idx="14">it</dependent>
          </dep>
          <dep type="cop">
            <governor idx="17">balls-up</governor>
            <dependent idx="15">became</dependent>
          </dep>
          <dep type="det">
            <governor idx="17">balls-up</governor>
            <dependent idx="16">the</dependent>
          </dep>
          <dep type="conj_but">
            <governor idx="3">making</governor>
            <dependent idx="17">balls-up</dependent>
          </dep>
          <dep type="poss">
            <governor idx="21">career</governor>
            <dependent idx="19">my</dependent>
          </dep>
          <dep type="nn">
            <governor idx="21">career</governor>
            <dependent idx="20">cooking</dependent>
          </dep>
          <dep type="prep_of">
            <governor idx="17">balls-up</governor>
            <dependent idx="21">career</dependent>
          </dep>
        </dependencies>
        <dependencies type="collapsed-ccprocessed-dependencies">
          <dep type="root">
            <governor idx="0">ROOT</governor>
            <dependent idx="3">making</dependent>
          </dep>
          <dep type="nsubj">
            <governor idx="3">making</governor>
            <dependent idx="1">I</dependent>
          </dep>
          <dep type="aux">
            <governor idx="3">making</governor>
            <dependent idx="2">was</dependent>
          </dep>
          <dep type="det">
            <governor idx="5">cake</governor>
            <dependent idx="4">a</dependent>
          </dep>
          <dep type="dobj">
            <governor idx="3">making</governor>
            <dependent idx="5">cake</dependent>
          </dep>
          <dep type="advmod">
            <governor idx="9">added</governor>
            <dependent idx="7">when</dependent>
          </dep>
          <dep type="nsubj">
            <governor idx="9">added</governor>
            <dependent idx="8">I</dependent>
          </dep>
          <dep type="advcl">
            <governor idx="17">balls-up</governor>
            <dependent idx="9">added</dependent>
          </dep>
          <dep type="advmod">
            <governor idx="11">much</governor>
            <dependent idx="10">too</dependent>
          </dep>
          <dep type="amod">
            <governor idx="12">sugar</governor>
            <dependent idx="11">much</dependent>
          </dep>
          <dep type="dobj">
            <governor idx="9">added</governor>
            <dependent idx="12">sugar</dependent>
          </dep>
          <dep type="nsubj">
            <governor idx="17">balls-up</governor>
            <dependent idx="14">it</dependent>
          </dep>
          <dep type="cop">
            <governor idx="17">balls-up</governor>
            <dependent idx="15">became</dependent>
          </dep>
          <dep type="det">
            <governor idx="17">balls-up</governor>
            <dependent idx="16">the</dependent>
          </dep>
          <dep type="conj_but">
            <governor idx="3">making</governor>
            <dependent idx="17">balls-up</dependent>
          </dep>
          <dep type="poss">
            <governor idx="21">career</governor>
            <dependent idx="19">my</dependent>
          </dep>
          <dep type="nn">
            <governor idx="21">career</governor>
            <dependent idx="20">cooking</dependent>
          </dep>
          <dep type="prep_of">
            <governor idx="17">balls-up</governor>
            <dependent idx="21">career</dependent>
          </dep>
        </dependencies>
      </sentence>
      <sentence id="2">
        <tokens>
          <token id="1">
            <word>the</word>
            <lemma>the</lemma>
            <CharacterOffsetBegin>98</CharacterOffsetBegin>
            <CharacterOffsetEnd>101</CharacterOffsetEnd>
            <POS>DT</POS>
          </token>
          <token id="2">
            <word>worst</word>
            <lemma>worst</lemma>
            <CharacterOffsetBegin>102</CharacterOffsetBegin>
            <CharacterOffsetEnd>107</CharacterOffsetEnd>
            <POS>JJS</POS>
          </token>
          <token id="3">
            <word>cooking</word>
            <lemma>cooking</lemma>
            <CharacterOffsetBegin>108</CharacterOffsetBegin>
            <CharacterOffsetEnd>115</CharacterOffsetEnd>
            <POS>NN</POS>
          </token>
          <token id="4">
            <word>mistake</word>
            <lemma>mistake</lemma>
            <CharacterOffsetBegin>116</CharacterOffsetBegin>
            <CharacterOffsetEnd>123</CharacterOffsetEnd>
            <POS>NN</POS>
          </token>
          <token id="5">
            <word>I</word>
            <lemma>I</lemma>
            <CharacterOffsetBegin>124</CharacterOffsetBegin>
            <CharacterOffsetEnd>125</CharacterOffsetEnd>
            <POS>PRP</POS>
          </token>
          <token id="6">
            <word>'ve</word>
            <lemma>have</lemma>
            <CharacterOffsetBegin>125</CharacterOffsetBegin>
            <CharacterOffsetEnd>128</CharacterOffsetEnd>
            <POS>VBP</POS>
          </token>
          <token id="7">
            <word>made</word>
            <lemma>make</lemma>
            <CharacterOffsetBegin>129</CharacterOffsetBegin>
            <CharacterOffsetEnd>133</CharacterOffsetEnd>
            <POS>VBN</POS>
          </token>
        </tokens>
        <parse>(ROOT (FRAG (NP (NP (DT the) (JJS worst) (NN cooking) (NN mistake)) (SBAR (S (NP (PRP I)) (VP (VBP 've) (VP (VBN made)))))))) </parse>
        <dependencies type="basic-dependencies">
          <dep type="root">
            <governor idx="0">ROOT</governor>
            <dependent idx="4">mistake</dependent>
          </dep>
          <dep type="det">
            <governor idx="4">mistake</governor>
            <dependent idx="1">the</dependent>
          </dep>
          <dep type="amod">
            <governor idx="4">mistake</governor>
            <dependent idx="2">worst</dependent>
          </dep>
          <dep type="nn">
            <governor idx="4">mistake</governor>
            <dependent idx="3">cooking</dependent>
          </dep>
          <dep type="nsubj">
            <governor idx="7">made</governor>
            <dependent idx="5">I</dependent>
          </dep>
          <dep type="aux">
            <governor idx="7">made</governor>
            <dependent idx="6">'ve</dependent>
          </dep>
          <dep type="rcmod">
            <governor idx="4">mistake</governor>
            <dependent idx="7">made</dependent>
          </dep>
        </dependencies>
        <dependencies type="collapsed-dependencies">
          <dep type="root">
            <governor idx="0">ROOT</governor>
            <dependent idx="4">mistake</dependent>
          </dep>
          <dep type="det">
            <governor idx="4">mistake</governor>
            <dependent idx="1">the</dependent>
          </dep>
          <dep type="amod">
            <governor idx="4">mistake</governor>
            <dependent idx="2">worst</dependent>
          </dep>
          <dep type="nn">
            <governor idx="4">mistake</governor>
            <dependent idx="3">cooking</dependent>
          </dep>
          <dep type="nsubj">
            <governor idx="7">made</governor>
            <dependent idx="5">I</dependent>
          </dep>
          <dep type="aux">
            <governor idx="7">made</governor>
            <dependent idx="6">'ve</dependent>
          </dep>
          <dep type="rcmod">
            <governor idx="4">mistake</governor>
            <dependent idx="7">made</dependent>
          </dep>
        </dependencies>
        <dependencies type="collapsed-ccprocessed-dependencies">
          <dep type="root">
            <governor idx="0">ROOT</governor>
            <dependent idx="4">mistake</dependent>
          </dep>
          <dep type="det">
            <governor idx="4">mistake</governor>
            <dependent idx="1">the</dependent>
          </dep>
          <dep type="amod">
            <governor idx="4">mistake</governor>
            <dependent idx="2">worst</dependent>
          </dep>
          <dep type="nn">
            <governor idx="4">mistake</governor>
            <dependent idx="3">cooking</dependent>
          </dep>
          <dep type="nsubj">
            <governor idx="7">made</governor>
            <dependent idx="5">I</dependent>
          </dep>
          <dep type="aux">
            <governor idx="7">made</governor>
            <dependent idx="6">'ve</dependent>
          </dep>
          <dep type="rcmod">
            <governor idx="4">mistake</governor>
            <dependent idx="7">made</dependent>
          </dep>
        </dependencies>
      </sentence>
    </sentences>
  </document>
</root>
