<?xml version="1.0" encoding="UTF-8"?>
<?xml-stylesheet href="CoreNLP-to-HTML.xsl" type="text/xsl"?>
<root>
  <document>
    <sentences>
      <sentence id="1">
        <tokens>
          <token id="1">
            <word>My</word>
            <lemma>my</lemma>
            <CharacterOffsetBegin>0</CharacterOffsetBegin>
            <CharacterOffsetEnd>2</CharacterOffsetEnd>
            <POS>PRP$</POS>
          </token>
          <token id="2">
            <word>slave-driving</word>
            <lemma>slave-driving</lemma>
            <CharacterOffsetBegin>3</CharacterOffsetBegin>
            <CharacterOffsetEnd>16</CharacterOffsetEnd>
            <POS>JJ</POS>
          </token>
          <token id="3">
            <word>boss</word>
            <lemma>boss</lemma>
            <CharacterOffsetBegin>17</CharacterOffsetBegin>
            <CharacterOffsetEnd>21</CharacterOffsetEnd>
            <POS>NN</POS>
          </token>
          <token id="4">
            <word>expects</word>
            <lemma>expect</lemma>
            <CharacterOffsetBegin>22</CharacterOffsetBegin>
            <CharacterOffsetEnd>29</CharacterOffsetEnd>
            <POS>VBZ</POS>
          </token>
          <token id="5">
            <word>me</word>
            <lemma>I</lemma>
            <CharacterOffsetBegin>30</CharacterOffsetBegin>
            <CharacterOffsetEnd>32</CharacterOffsetEnd>
            <POS>PRP</POS>
          </token>
          <token id="6">
            <word>to</word>
            <lemma>to</lemma>
            <CharacterOffsetBegin>33</CharacterOffsetBegin>
            <CharacterOffsetEnd>35</CharacterOffsetEnd>
            <POS>TO</POS>
          </token>
          <token id="7">
            <word>work</word>
            <lemma>work</lemma>
            <CharacterOffsetBegin>36</CharacterOffsetBegin>
            <CharacterOffsetEnd>40</CharacterOffsetEnd>
            <POS>VB</POS>
          </token>
          <token id="8">
            <word>over</word>
            <lemma>over</lemma>
            <CharacterOffsetBegin>41</CharacterOffsetBegin>
            <CharacterOffsetEnd>45</CharacterOffsetEnd>
            <POS>IN</POS>
          </token>
          <token id="9">
            <word>the</word>
            <lemma>the</lemma>
            <CharacterOffsetBegin>46</CharacterOffsetBegin>
            <CharacterOffsetEnd>49</CharacterOffsetEnd>
            <POS>DT</POS>
          </token>
          <token id="10">
            <word>weekend</word>
            <lemma>weekend</lemma>
            <CharacterOffsetBegin>50</CharacterOffsetBegin>
            <CharacterOffsetEnd>57</CharacterOffsetEnd>
            <POS>NN</POS>
          </token>
          <token id="11">
            <word>-</word>
            <lemma>-</lemma>
            <CharacterOffsetBegin>58</CharacterOffsetBegin>
            <CharacterOffsetEnd>59</CharacterOffsetEnd>
            <POS>:</POS>
          </token>
          <token id="12">
            <word>what</word>
            <lemma>what</lemma>
            <CharacterOffsetBegin>60</CharacterOffsetBegin>
            <CharacterOffsetEnd>64</CharacterOffsetEnd>
            <POS>WP</POS>
          </token>
          <token id="13">
            <word>a</word>
            <lemma>a</lemma>
            <CharacterOffsetBegin>65</CharacterOffsetBegin>
            <CharacterOffsetEnd>66</CharacterOffsetEnd>
            <POS>DT</POS>
          </token>
          <token id="14">
            <word>ball-breaker</word>
            <lemma>ball-breaker</lemma>
            <CharacterOffsetBegin>67</CharacterOffsetBegin>
            <CharacterOffsetEnd>79</CharacterOffsetEnd>
            <POS>NN</POS>
          </token>
          <token id="15">
            <word>!</word>
            <lemma>!</lemma>
            <CharacterOffsetBegin>79</CharacterOffsetBegin>
            <CharacterOffsetEnd>80</CharacterOffsetEnd>
            <POS>.</POS>
          </token>
        </tokens>
        <parse>(ROOT (S (S (NP (PRP$ My) (JJ slave-driving) (NN boss)) (VP (VBZ expects) (S (NP (PRP me)) (VP (TO to) (VP (VB work) (PP (IN over) (NP (DT the) (NN weekend)))))))) (: -) (FRAG (X (WP what)) (NP (DT a) (NN ball-breaker))) (. !))) </parse>
        <dependencies type="basic-dependencies">
          <dep type="root">
            <governor idx="0">ROOT</governor>
            <dependent idx="4">expects</dependent>
          </dep>
          <dep type="poss">
            <governor idx="3">boss</governor>
            <dependent idx="1">My</dependent>
          </dep>
          <dep type="amod">
            <governor idx="3">boss</governor>
            <dependent idx="2">slave-driving</dependent>
          </dep>
          <dep type="nsubj">
            <governor idx="4">expects</governor>
            <dependent idx="3">boss</dependent>
          </dep>
          <dep type="nsubj">
            <governor idx="7">work</governor>
            <dependent idx="5">me</dependent>
          </dep>
          <dep type="aux">
            <governor idx="7">work</governor>
            <dependent idx="6">to</dependent>
          </dep>
          <dep type="xcomp">
            <governor idx="4">expects</governor>
            <dependent idx="7">work</dependent>
          </dep>
          <dep type="prep">
            <governor idx="7">work</governor>
            <dependent idx="8">over</dependent>
          </dep>
          <dep type="det">
            <governor idx="10">weekend</governor>
            <dependent idx="9">the</dependent>
          </dep>
          <dep type="pobj">
            <governor idx="8">over</governor>
            <dependent idx="10">weekend</dependent>
          </dep>
          <dep type="dep">
            <governor idx="14">ball-breaker</governor>
            <dependent idx="12">what</dependent>
          </dep>
          <dep type="det">
            <governor idx="14">ball-breaker</governor>
            <dependent idx="13">a</dependent>
          </dep>
          <dep type="dep">
            <governor idx="4">expects</governor>
            <dependent idx="14">ball-breaker</dependent>
          </dep>
        </dependencies>
        <dependencies type="collapsed-dependencies">
          <dep type="root">
            <governor idx="0">ROOT</governor>
            <dependent idx="4">expects</dependent>
          </dep>
          <dep type="poss">
            <governor idx="3">boss</governor>
            <dependent idx="1">My</dependent>
          </dep>
          <dep type="amod">
            <governor idx="3">boss</governor>
            <dependent idx="2">slave-driving</dependent>
          </dep>
          <dep type="nsubj">
            <governor idx="4">expects</governor>
            <dependent idx="3">boss</dependent>
          </dep>
          <dep type="nsubj">
            <governor idx="7">work</governor>
            <dependent idx="5">me</dependent>
          </dep>
          <dep type="aux">
            <governor idx="7">work</governor>
            <dependent idx="6">to</dependent>
          </dep>
          <dep type="xcomp">
            <governor idx="4">expects</governor>
            <dependent idx="7">work</dependent>
          </dep>
          <dep type="det">
            <governor idx="10">weekend</governor>
            <dependent idx="9">the</dependent>
          </dep>
          <dep type="prep_over">
            <governor idx="7">work</governor>
            <dependent idx="10">weekend</dependent>
          </dep>
          <dep type="dep">
            <governor idx="14">ball-breaker</governor>
            <dependent idx="12">what</dependent>
          </dep>
          <dep type="det">
            <governor idx="14">ball-breaker</governor>
            <dependent idx="13">a</dependent>
          </dep>
          <dep type="dep">
            <governor idx="4">expects</governor>
            <dependent idx="14">ball-breaker</dependent>
          </dep>
        </dependencies>
        <dependencies type="collapsed-ccprocessed-dependencies">
          <dep type="root">
            <governor idx="0">ROOT</governor>
            <dependent idx="4">expects</dependent>
          </dep>
          <dep type="poss">
            <governor idx="3">boss</governor>
            <dependent idx="1">My</dependent>
          </dep>
          <dep type="amod">
            <governor idx="3">boss</governor>
            <dependent idx="2">slave-driving</dependent>
          </dep>
          <dep type="nsubj">
            <governor idx="4">expects</governor>
            <dependent idx="3">boss</dependent>
          </dep>
          <dep type="nsubj">
            <governor idx="7">work</governor>
            <dependent idx="5">me</dependent>
          </dep>
          <dep type="aux">
            <governor idx="7">work</governor>
            <dependent idx="6">to</dependent>
          </dep>
          <dep type="xcomp">
            <governor idx="4">expects</governor>
            <dependent idx="7">work</dependent>
          </dep>
          <dep type="det">
            <governor idx="10">weekend</governor>
            <dependent idx="9">the</dependent>
          </dep>
          <dep type="prep_over">
            <governor idx="7">work</governor>
            <dependent idx="10">weekend</dependent>
          </dep>
          <dep type="dep">
            <governor idx="14">ball-breaker</governor>
            <dependent idx="12">what</dependent>
          </dep>
          <dep type="det">
            <governor idx="14">ball-breaker</governor>
            <dependent idx="13">a</dependent>
          </dep>
          <dep type="dep">
            <governor idx="4">expects</governor>
            <dependent idx="14">ball-breaker</dependent>
          </dep>
        </dependencies>
      </sentence>
      <sentence id="2">
        <tokens>
          <token id="1">
            <word>unappealing</word>
            <lemma>unappealing</lemma>
            <CharacterOffsetBegin>81</CharacterOffsetBegin>
            <CharacterOffsetEnd>92</CharacterOffsetEnd>
            <POS>JJ</POS>
          </token>
          <token id="2">
            <word>work</word>
            <lemma>work</lemma>
            <CharacterOffsetBegin>93</CharacterOffsetBegin>
            <CharacterOffsetEnd>97</CharacterOffsetEnd>
            <POS>NN</POS>
          </token>
          <token id="3">
            <word>on</word>
            <lemma>on</lemma>
            <CharacterOffsetBegin>98</CharacterOffsetBegin>
            <CharacterOffsetEnd>100</CharacterOffsetEnd>
            <POS>IN</POS>
          </token>
          <token id="4">
            <word>the</word>
            <lemma>the</lemma>
            <CharacterOffsetBegin>101</CharacterOffsetBegin>
            <CharacterOffsetEnd>104</CharacterOffsetEnd>
            <POS>DT</POS>
          </token>
          <token id="5">
            <word>weekend</word>
            <lemma>weekend</lemma>
            <CharacterOffsetBegin>105</CharacterOffsetBegin>
            <CharacterOffsetEnd>112</CharacterOffsetEnd>
            <POS>NN</POS>
          </token>
        </tokens>
        <parse>(ROOT (NP (NP (JJ unappealing) (NN work)) (PP (IN on) (NP (DT the) (NN weekend))))) </parse>
        <dependencies type="basic-dependencies">
          <dep type="root">
            <governor idx="0">ROOT</governor>
            <dependent idx="2">work</dependent>
          </dep>
          <dep type="amod">
            <governor idx="2">work</governor>
            <dependent idx="1">unappealing</dependent>
          </dep>
          <dep type="prep">
            <governor idx="2">work</governor>
            <dependent idx="3">on</dependent>
          </dep>
          <dep type="det">
            <governor idx="5">weekend</governor>
            <dependent idx="4">the</dependent>
          </dep>
          <dep type="pobj">
            <governor idx="3">on</governor>
            <dependent idx="5">weekend</dependent>
          </dep>
        </dependencies>
        <dependencies type="collapsed-dependencies">
          <dep type="root">
            <governor idx="0">ROOT</governor>
            <dependent idx="2">work</dependent>
          </dep>
          <dep type="amod">
            <governor idx="2">work</governor>
            <dependent idx="1">unappealing</dependent>
          </dep>
          <dep type="det">
            <governor idx="5">weekend</governor>
            <dependent idx="4">the</dependent>
          </dep>
          <dep type="prep_on">
            <governor idx="2">work</governor>
            <dependent idx="5">weekend</dependent>
          </dep>
        </dependencies>
        <dependencies type="collapsed-ccprocessed-dependencies">
          <dep type="root">
            <governor idx="0">ROOT</governor>
            <dependent idx="2">work</dependent>
          </dep>
          <dep type="amod">
            <governor idx="2">work</governor>
            <dependent idx="1">unappealing</dependent>
          </dep>
          <dep type="det">
            <governor idx="5">weekend</governor>
            <dependent idx="4">the</dependent>
          </dep>
          <dep type="prep_on">
            <governor idx="2">work</governor>
            <dependent idx="5">weekend</dependent>
          </dep>
        </dependencies>
      </sentence>
    </sentences>
  </document>
</root>
