<?xml version="1.0" encoding="UTF-8"?>
<?xml-stylesheet href="CoreNLP-to-HTML.xsl" type="text/xsl"?>
<root>
  <document>
    <sentences>
      <sentence id="1">
        <tokens>
          <token id="1">
            <word>There</word>
            <lemma>there</lemma>
            <CharacterOffsetBegin>0</CharacterOffsetBegin>
            <CharacterOffsetEnd>5</CharacterOffsetEnd>
            <POS>EX</POS>
          </token>
          <token id="2">
            <word>must</word>
            <lemma>must</lemma>
            <CharacterOffsetBegin>6</CharacterOffsetBegin>
            <CharacterOffsetEnd>10</CharacterOffsetEnd>
            <POS>MD</POS>
          </token>
          <token id="3">
            <word>be</word>
            <lemma>be</lemma>
            <CharacterOffsetBegin>11</CharacterOffsetBegin>
            <CharacterOffsetEnd>13</CharacterOffsetEnd>
            <POS>VB</POS>
          </token>
          <token id="4">
            <word>a</word>
            <lemma>a</lemma>
            <CharacterOffsetBegin>14</CharacterOffsetBegin>
            <CharacterOffsetEnd>15</CharacterOffsetEnd>
            <POS>DT</POS>
          </token>
          <token id="5">
            <word>clear</word>
            <lemma>clear</lemma>
            <CharacterOffsetBegin>16</CharacterOffsetBegin>
            <CharacterOffsetEnd>21</CharacterOffsetEnd>
            <POS>JJ</POS>
          </token>
          <token id="6">
            <word>signal</word>
            <lemma>signal</lemma>
            <CharacterOffsetBegin>22</CharacterOffsetBegin>
            <CharacterOffsetEnd>28</CharacterOffsetEnd>
            <POS>NN</POS>
          </token>
          <token id="7">
            <word>to</word>
            <lemma>to</lemma>
            <CharacterOffsetBegin>29</CharacterOffsetBegin>
            <CharacterOffsetEnd>31</CharacterOffsetEnd>
            <POS>TO</POS>
          </token>
          <token id="8">
            <word>sub-standard</word>
            <lemma>sub-standard</lemma>
            <CharacterOffsetBegin>32</CharacterOffsetBegin>
            <CharacterOffsetEnd>44</CharacterOffsetEnd>
            <POS>JJ</POS>
          </token>
          <token id="9">
            <word>ships</word>
            <lemma>ship</lemma>
            <CharacterOffsetBegin>45</CharacterOffsetBegin>
            <CharacterOffsetEnd>50</CharacterOffsetEnd>
            <POS>NNS</POS>
          </token>
          <token id="10">
            <word>that</word>
            <lemma>that</lemma>
            <CharacterOffsetBegin>51</CharacterOffsetBegin>
            <CharacterOffsetEnd>55</CharacterOffsetEnd>
            <POS>IN</POS>
          </token>
          <token id="11">
            <word>we</word>
            <lemma>we</lemma>
            <CharacterOffsetBegin>56</CharacterOffsetBegin>
            <CharacterOffsetEnd>58</CharacterOffsetEnd>
            <POS>PRP</POS>
          </token>
          <token id="12">
            <word>will</word>
            <lemma>will</lemma>
            <CharacterOffsetBegin>59</CharacterOffsetBegin>
            <CharacterOffsetEnd>63</CharacterOffsetEnd>
            <POS>MD</POS>
          </token>
          <token id="13">
            <word>not</word>
            <lemma>not</lemma>
            <CharacterOffsetBegin>64</CharacterOffsetBegin>
            <CharacterOffsetEnd>67</CharacterOffsetEnd>
            <POS>RB</POS>
          </token>
          <token id="14">
            <word>tolerate</word>
            <lemma>tolerate</lemma>
            <CharacterOffsetBegin>68</CharacterOffsetBegin>
            <CharacterOffsetEnd>76</CharacterOffsetEnd>
            <POS>VB</POS>
          </token>
          <token id="15">
            <word>them</word>
            <lemma>they</lemma>
            <CharacterOffsetBegin>77</CharacterOffsetBegin>
            <CharacterOffsetEnd>81</CharacterOffsetEnd>
            <POS>PRP</POS>
          </token>
          <token id="16">
            <word>in</word>
            <lemma>in</lemma>
            <CharacterOffsetBegin>82</CharacterOffsetBegin>
            <CharacterOffsetEnd>84</CharacterOffsetEnd>
            <POS>IN</POS>
          </token>
          <token id="17">
            <word>European</word>
            <lemma>european</lemma>
            <CharacterOffsetBegin>85</CharacterOffsetBegin>
            <CharacterOffsetEnd>93</CharacterOffsetEnd>
            <POS>JJ</POS>
          </token>
          <token id="18">
            <word>waters</word>
            <lemma>water</lemma>
            <CharacterOffsetBegin>94</CharacterOffsetBegin>
            <CharacterOffsetEnd>100</CharacterOffsetEnd>
            <POS>NNS</POS>
          </token>
          <token id="19">
            <word>or</word>
            <lemma>or</lemma>
            <CharacterOffsetBegin>101</CharacterOffsetBegin>
            <CharacterOffsetEnd>103</CharacterOffsetEnd>
            <POS>CC</POS>
          </token>
          <token id="20">
            <word>in</word>
            <lemma>in</lemma>
            <CharacterOffsetBegin>104</CharacterOffsetBegin>
            <CharacterOffsetEnd>106</CharacterOffsetEnd>
            <POS>IN</POS>
          </token>
          <token id="21">
            <word>European</word>
            <lemma>european</lemma>
            <CharacterOffsetBegin>107</CharacterOffsetBegin>
            <CharacterOffsetEnd>115</CharacterOffsetEnd>
            <POS>JJ</POS>
          </token>
          <token id="22">
            <word>ports</word>
            <lemma>port</lemma>
            <CharacterOffsetBegin>116</CharacterOffsetBegin>
            <CharacterOffsetEnd>121</CharacterOffsetEnd>
            <POS>NNS</POS>
          </token>
          <token id="23">
            <word>.</word>
            <lemma>.</lemma>
            <CharacterOffsetBegin>121</CharacterOffsetBegin>
            <CharacterOffsetEnd>122</CharacterOffsetEnd>
            <POS>.</POS>
          </token>
        </tokens>
        <parse>(ROOT (S (NP (EX There)) (VP (MD must) (VP (VB be) (NP (DT a) (JJ clear) (NN signal)) (PP (TO to) (NP (JJ sub-standard) (NNS ships))) (SBAR (IN that) (S (NP (PRP we)) (VP (MD will) (RB not) (VP (VB tolerate) (NP (PRP them)) (PP (PP (IN in) (NP (JJ European) (NNS waters))) (CC or) (PP (IN in) (NP (JJ European) (NNS ports)))))))))) (. .))) </parse>
        <dependencies type="basic-dependencies">
          <dep type="root">
            <governor idx="0">ROOT</governor>
            <dependent idx="6">signal</dependent>
          </dep>
          <dep type="expl">
            <governor idx="6">signal</governor>
            <dependent idx="1">There</dependent>
          </dep>
          <dep type="aux">
            <governor idx="6">signal</governor>
            <dependent idx="2">must</dependent>
          </dep>
          <dep type="cop">
            <governor idx="6">signal</governor>
            <dependent idx="3">be</dependent>
          </dep>
          <dep type="det">
            <governor idx="6">signal</governor>
            <dependent idx="4">a</dependent>
          </dep>
          <dep type="amod">
            <governor idx="6">signal</governor>
            <dependent idx="5">clear</dependent>
          </dep>
          <dep type="prep">
            <governor idx="6">signal</governor>
            <dependent idx="7">to</dependent>
          </dep>
          <dep type="amod">
            <governor idx="9">ships</governor>
            <dependent idx="8">sub-standard</dependent>
          </dep>
          <dep type="pobj">
            <governor idx="7">to</governor>
            <dependent idx="9">ships</dependent>
          </dep>
          <dep type="mark">
            <governor idx="14">tolerate</governor>
            <dependent idx="10">that</dependent>
          </dep>
          <dep type="nsubj">
            <governor idx="14">tolerate</governor>
            <dependent idx="11">we</dependent>
          </dep>
          <dep type="aux">
            <governor idx="14">tolerate</governor>
            <dependent idx="12">will</dependent>
          </dep>
          <dep type="neg">
            <governor idx="14">tolerate</governor>
            <dependent idx="13">not</dependent>
          </dep>
          <dep type="ccomp">
            <governor idx="6">signal</governor>
            <dependent idx="14">tolerate</dependent>
          </dep>
          <dep type="dobj">
            <governor idx="14">tolerate</governor>
            <dependent idx="15">them</dependent>
          </dep>
          <dep type="prep">
            <governor idx="14">tolerate</governor>
            <dependent idx="16">in</dependent>
          </dep>
          <dep type="amod">
            <governor idx="18">waters</governor>
            <dependent idx="17">European</dependent>
          </dep>
          <dep type="pobj">
            <governor idx="16">in</governor>
            <dependent idx="18">waters</dependent>
          </dep>
          <dep type="cc">
            <governor idx="16">in</governor>
            <dependent idx="19">or</dependent>
          </dep>
          <dep type="conj">
            <governor idx="16">in</governor>
            <dependent idx="20">in</dependent>
          </dep>
          <dep type="amod">
            <governor idx="22">ports</governor>
            <dependent idx="21">European</dependent>
          </dep>
          <dep type="pobj">
            <governor idx="20">in</governor>
            <dependent idx="22">ports</dependent>
          </dep>
        </dependencies>
        <dependencies type="collapsed-dependencies">
          <dep type="root">
            <governor idx="0">ROOT</governor>
            <dependent idx="6">signal</dependent>
          </dep>
          <dep type="expl">
            <governor idx="6">signal</governor>
            <dependent idx="1">There</dependent>
          </dep>
          <dep type="aux">
            <governor idx="6">signal</governor>
            <dependent idx="2">must</dependent>
          </dep>
          <dep type="cop">
            <governor idx="6">signal</governor>
            <dependent idx="3">be</dependent>
          </dep>
          <dep type="det">
            <governor idx="6">signal</governor>
            <dependent idx="4">a</dependent>
          </dep>
          <dep type="amod">
            <governor idx="6">signal</governor>
            <dependent idx="5">clear</dependent>
          </dep>
          <dep type="amod">
            <governor idx="9">ships</governor>
            <dependent idx="8">sub-standard</dependent>
          </dep>
          <dep type="prep_to">
            <governor idx="6">signal</governor>
            <dependent idx="9">ships</dependent>
          </dep>
          <dep type="mark">
            <governor idx="14">tolerate</governor>
            <dependent idx="10">that</dependent>
          </dep>
          <dep type="nsubj">
            <governor idx="14">tolerate</governor>
            <dependent idx="11">we</dependent>
          </dep>
          <dep type="aux">
            <governor idx="14">tolerate</governor>
            <dependent idx="12">will</dependent>
          </dep>
          <dep type="neg">
            <governor idx="14">tolerate</governor>
            <dependent idx="13">not</dependent>
          </dep>
          <dep type="ccomp">
            <governor idx="6">signal</governor>
            <dependent idx="14">tolerate</dependent>
          </dep>
          <dep type="dobj">
            <governor idx="14">tolerate</governor>
            <dependent idx="15">them</dependent>
          </dep>
          <dep type="amod">
            <governor idx="18">waters</governor>
            <dependent idx="17">European</dependent>
          </dep>
          <dep type="prep_in">
            <governor idx="14">tolerate</governor>
            <dependent idx="18">waters</dependent>
          </dep>
          <dep type="amod">
            <governor idx="22">ports</governor>
            <dependent idx="21">European</dependent>
          </dep>
          <dep type="conj_or">
            <governor idx="18">waters</governor>
            <dependent idx="22">ports</dependent>
          </dep>
        </dependencies>
        <dependencies type="collapsed-ccprocessed-dependencies">
          <dep type="root">
            <governor idx="0">ROOT</governor>
            <dependent idx="6">signal</dependent>
          </dep>
          <dep type="expl">
            <governor idx="6">signal</governor>
            <dependent idx="1">There</dependent>
          </dep>
          <dep type="aux">
            <governor idx="6">signal</governor>
            <dependent idx="2">must</dependent>
          </dep>
          <dep type="cop">
            <governor idx="6">signal</governor>
            <dependent idx="3">be</dependent>
          </dep>
          <dep type="det">
            <governor idx="6">signal</governor>
            <dependent idx="4">a</dependent>
          </dep>
          <dep type="amod">
            <governor idx="6">signal</governor>
            <dependent idx="5">clear</dependent>
          </dep>
          <dep type="amod">
            <governor idx="9">ships</governor>
            <dependent idx="8">sub-standard</dependent>
          </dep>
          <dep type="prep_to">
            <governor idx="6">signal</governor>
            <dependent idx="9">ships</dependent>
          </dep>
          <dep type="mark">
            <governor idx="14">tolerate</governor>
            <dependent idx="10">that</dependent>
          </dep>
          <dep type="nsubj">
            <governor idx="14">tolerate</governor>
            <dependent idx="11">we</dependent>
          </dep>
          <dep type="aux">
            <governor idx="14">tolerate</governor>
            <dependent idx="12">will</dependent>
          </dep>
          <dep type="neg">
            <governor idx="14">tolerate</governor>
            <dependent idx="13">not</dependent>
          </dep>
          <dep type="ccomp">
            <governor idx="6">signal</governor>
            <dependent idx="14">tolerate</dependent>
          </dep>
          <dep type="dobj">
            <governor idx="14">tolerate</governor>
            <dependent idx="15">them</dependent>
          </dep>
          <dep type="amod">
            <governor idx="18">waters</governor>
            <dependent idx="17">European</dependent>
          </dep>
          <dep type="prep_in">
            <governor idx="14">tolerate</governor>
            <dependent idx="18">waters</dependent>
          </dep>
          <dep type="amod">
            <governor idx="22">ports</governor>
            <dependent idx="21">European</dependent>
          </dep>
          <dep type="prep_in">
            <governor idx="14">tolerate</governor>
            <dependent idx="22">ports</dependent>
          </dep>
          <dep type="conj_or">
            <governor idx="18">waters</governor>
            <dependent idx="22">ports</dependent>
          </dep>
        </dependencies>
      </sentence>
      <sentence id="2">
        <tokens>
          <token id="1">
            <word>humanitarian</word>
            <lemma>humanitarian</lemma>
            <CharacterOffsetBegin>123</CharacterOffsetBegin>
            <CharacterOffsetEnd>135</CharacterOffsetEnd>
            <POS>JJ</POS>
          </token>
          <token id="2">
            <word>aid</word>
            <lemma>aid</lemma>
            <CharacterOffsetBegin>136</CharacterOffsetBegin>
            <CharacterOffsetEnd>139</CharacterOffsetEnd>
            <POS>NN</POS>
          </token>
        </tokens>
        <parse>(ROOT (NP (JJ humanitarian) (NN aid))) </parse>
        <dependencies type="basic-dependencies">
          <dep type="root">
            <governor idx="0">ROOT</governor>
            <dependent idx="2">aid</dependent>
          </dep>
          <dep type="amod">
            <governor idx="2">aid</governor>
            <dependent idx="1">humanitarian</dependent>
          </dep>
        </dependencies>
        <dependencies type="collapsed-dependencies">
          <dep type="root">
            <governor idx="0">ROOT</governor>
            <dependent idx="2">aid</dependent>
          </dep>
          <dep type="amod">
            <governor idx="2">aid</governor>
            <dependent idx="1">humanitarian</dependent>
          </dep>
        </dependencies>
        <dependencies type="collapsed-ccprocessed-dependencies">
          <dep type="root">
            <governor idx="0">ROOT</governor>
            <dependent idx="2">aid</dependent>
          </dep>
          <dep type="amod">
            <governor idx="2">aid</governor>
            <dependent idx="1">humanitarian</dependent>
          </dep>
        </dependencies>
      </sentence>
    </sentences>
  </document>
</root>
