<?xml version="1.0" encoding="UTF-8"?>
<?xml-stylesheet href="CoreNLP-to-HTML.xsl" type="text/xsl"?>
<root>
  <document>
    <sentences>
      <sentence id="1">
        <tokens>
          <token id="1">
            <word>Malaysia</word>
            <lemma>Malaysia</lemma>
            <CharacterOffsetBegin>0</CharacterOffsetBegin>
            <CharacterOffsetEnd>8</CharacterOffsetEnd>
            <POS>NNP</POS>
          </token>
          <token id="2">
            <word>has</word>
            <lemma>have</lemma>
            <CharacterOffsetBegin>9</CharacterOffsetBegin>
            <CharacterOffsetEnd>12</CharacterOffsetEnd>
            <POS>VBZ</POS>
          </token>
          <token id="3">
            <word>decided</word>
            <lemma>decide</lemma>
            <CharacterOffsetBegin>13</CharacterOffsetBegin>
            <CharacterOffsetEnd>20</CharacterOffsetEnd>
            <POS>VBN</POS>
          </token>
          <token id="4">
            <word>to</word>
            <lemma>to</lemma>
            <CharacterOffsetBegin>21</CharacterOffsetBegin>
            <CharacterOffsetEnd>23</CharacterOffsetEnd>
            <POS>TO</POS>
          </token>
          <token id="5">
            <word>postone</word>
            <lemma>postone</lemma>
            <CharacterOffsetBegin>24</CharacterOffsetBegin>
            <CharacterOffsetEnd>31</CharacterOffsetEnd>
            <POS>VB</POS>
          </token>
          <token id="6">
            <word>development</word>
            <lemma>development</lemma>
            <CharacterOffsetBegin>32</CharacterOffsetBegin>
            <CharacterOffsetEnd>43</CharacterOffsetEnd>
            <POS>NN</POS>
          </token>
          <token id="7">
            <word>of</word>
            <lemma>of</lemma>
            <CharacterOffsetBegin>44</CharacterOffsetBegin>
            <CharacterOffsetEnd>46</CharacterOffsetEnd>
            <POS>IN</POS>
          </token>
          <token id="8">
            <word>a</word>
            <lemma>a</lemma>
            <CharacterOffsetBegin>47</CharacterOffsetBegin>
            <CharacterOffsetEnd>48</CharacterOffsetEnd>
            <POS>DT</POS>
          </token>
          <token id="9">
            <word>five</word>
            <lemma>five</lemma>
            <CharacterOffsetBegin>49</CharacterOffsetBegin>
            <CharacterOffsetEnd>53</CharacterOffsetEnd>
            <POS>CD</POS>
          </token>
          <token id="10">
            <word>billion</word>
            <lemma>billion</lemma>
            <CharacterOffsetBegin>54</CharacterOffsetBegin>
            <CharacterOffsetEnd>61</CharacterOffsetEnd>
            <POS>CD</POS>
          </token>
          <token id="11">
            <word>dlr</word>
            <lemma>dlr</lemma>
            <CharacterOffsetBegin>62</CharacterOffsetBegin>
            <CharacterOffsetEnd>65</CharacterOffsetEnd>
            <POS>NN</POS>
          </token>
          <token id="12">
            <word>hydroelectric</word>
            <lemma>hydroelectric</lemma>
            <CharacterOffsetBegin>66</CharacterOffsetBegin>
            <CharacterOffsetEnd>79</CharacterOffsetEnd>
            <POS>JJ</POS>
          </token>
          <token id="13">
            <word>power</word>
            <lemma>power</lemma>
            <CharacterOffsetBegin>80</CharacterOffsetBegin>
            <CharacterOffsetEnd>85</CharacterOffsetEnd>
            <POS>NN</POS>
          </token>
          <token id="14">
            <word>project</word>
            <lemma>project</lemma>
            <CharacterOffsetBegin>86</CharacterOffsetBegin>
            <CharacterOffsetEnd>93</CharacterOffsetEnd>
            <POS>NN</POS>
          </token>
          <token id="15">
            <word>in</word>
            <lemma>in</lemma>
            <CharacterOffsetBegin>94</CharacterOffsetBegin>
            <CharacterOffsetEnd>96</CharacterOffsetEnd>
            <POS>IN</POS>
          </token>
          <token id="16">
            <word>Sarawak</word>
            <lemma>Sarawak</lemma>
            <CharacterOffsetBegin>97</CharacterOffsetBegin>
            <CharacterOffsetEnd>104</CharacterOffsetEnd>
            <POS>NNP</POS>
          </token>
          <token id="17">
            <word>,</word>
            <lemma>,</lemma>
            <CharacterOffsetBegin>104</CharacterOffsetBegin>
            <CharacterOffsetEnd>105</CharacterOffsetEnd>
            <POS>,</POS>
          </token>
          <token id="18">
            <word>East</word>
            <lemma>East</lemma>
            <CharacterOffsetBegin>106</CharacterOffsetBegin>
            <CharacterOffsetEnd>110</CharacterOffsetEnd>
            <POS>NNP</POS>
          </token>
          <token id="19">
            <word>Malaysia</word>
            <lemma>Malaysia</lemma>
            <CharacterOffsetBegin>111</CharacterOffsetBegin>
            <CharacterOffsetEnd>119</CharacterOffsetEnd>
            <POS>NNP</POS>
          </token>
          <token id="20">
            <word>,</word>
            <lemma>,</lemma>
            <CharacterOffsetBegin>119</CharacterOffsetBegin>
            <CharacterOffsetEnd>120</CharacterOffsetEnd>
            <POS>,</POS>
          </token>
          <token id="21">
            <word>until</word>
            <lemma>until</lemma>
            <CharacterOffsetBegin>121</CharacterOffsetBegin>
            <CharacterOffsetEnd>126</CharacterOffsetEnd>
            <POS>IN</POS>
          </token>
          <token id="22">
            <word>the</word>
            <lemma>the</lemma>
            <CharacterOffsetBegin>127</CharacterOffsetBegin>
            <CharacterOffsetEnd>130</CharacterOffsetEnd>
            <POS>DT</POS>
          </token>
          <token id="23">
            <word>economy</word>
            <lemma>economy</lemma>
            <CharacterOffsetBegin>131</CharacterOffsetBegin>
            <CharacterOffsetEnd>138</CharacterOffsetEnd>
            <POS>NN</POS>
          </token>
          <token id="24">
            <word>improves</word>
            <lemma>improve</lemma>
            <CharacterOffsetBegin>139</CharacterOffsetBegin>
            <CharacterOffsetEnd>147</CharacterOffsetEnd>
            <POS>VBZ</POS>
          </token>
          <token id="25">
            <word>,</word>
            <lemma>,</lemma>
            <CharacterOffsetBegin>147</CharacterOffsetBegin>
            <CharacterOffsetEnd>148</CharacterOffsetEnd>
            <POS>,</POS>
          </token>
          <token id="26">
            <word>deputy</word>
            <lemma>deputy</lemma>
            <CharacterOffsetBegin>149</CharacterOffsetBegin>
            <CharacterOffsetEnd>155</CharacterOffsetEnd>
            <POS>NN</POS>
          </token>
          <token id="27">
            <word>Minister</word>
            <lemma>Minister</lemma>
            <CharacterOffsetBegin>156</CharacterOffsetBegin>
            <CharacterOffsetEnd>164</CharacterOffsetEnd>
            <POS>NNP</POS>
          </token>
          <token id="28">
            <word>of</word>
            <lemma>of</lemma>
            <CharacterOffsetBegin>165</CharacterOffsetBegin>
            <CharacterOffsetEnd>167</CharacterOffsetEnd>
            <POS>IN</POS>
          </token>
          <token id="29">
            <word>Energy</word>
            <lemma>Energy</lemma>
            <CharacterOffsetBegin>168</CharacterOffsetBegin>
            <CharacterOffsetEnd>174</CharacterOffsetEnd>
            <POS>NNP</POS>
          </token>
          <token id="30">
            <word>,</word>
            <lemma>,</lemma>
            <CharacterOffsetBegin>174</CharacterOffsetBegin>
            <CharacterOffsetEnd>175</CharacterOffsetEnd>
            <POS>,</POS>
          </token>
          <token id="31">
            <word>Telecoms</word>
            <lemma>Telecoms</lemma>
            <CharacterOffsetBegin>176</CharacterOffsetBegin>
            <CharacterOffsetEnd>184</CharacterOffsetEnd>
            <POS>NNP</POS>
          </token>
          <token id="32">
            <word>and</word>
            <lemma>and</lemma>
            <CharacterOffsetBegin>185</CharacterOffsetBegin>
            <CharacterOffsetEnd>188</CharacterOffsetEnd>
            <POS>CC</POS>
          </token>
          <token id="33">
            <word>Post</word>
            <lemma>Post</lemma>
            <CharacterOffsetBegin>189</CharacterOffsetBegin>
            <CharacterOffsetEnd>193</CharacterOffsetEnd>
            <POS>NNP</POS>
          </token>
          <token id="34">
            <word>Zainal</word>
            <lemma>Zainal</lemma>
            <CharacterOffsetBegin>194</CharacterOffsetBegin>
            <CharacterOffsetEnd>200</CharacterOffsetEnd>
            <POS>NNP</POS>
          </token>
          <token id="35">
            <word>Abidin</word>
            <lemma>Abidin</lemma>
            <CharacterOffsetBegin>201</CharacterOffsetBegin>
            <CharacterOffsetEnd>207</CharacterOffsetEnd>
            <POS>NNP</POS>
          </token>
          <token id="36">
            <word>Zin</word>
            <lemma>Zin</lemma>
            <CharacterOffsetBegin>208</CharacterOffsetBegin>
            <CharacterOffsetEnd>211</CharacterOffsetEnd>
            <POS>NNP</POS>
          </token>
          <token id="37">
            <word>said</word>
            <lemma>say</lemma>
            <CharacterOffsetBegin>212</CharacterOffsetBegin>
            <CharacterOffsetEnd>216</CharacterOffsetEnd>
            <POS>VBD</POS>
          </token>
          <token id="38">
            <word>.</word>
            <lemma>.</lemma>
            <CharacterOffsetBegin>216</CharacterOffsetBegin>
            <CharacterOffsetEnd>217</CharacterOffsetEnd>
            <POS>.</POS>
          </token>
        </tokens>
        <parse>(ROOT (S (S (NP (NNP Malaysia)) (VP (VBZ has) (VP (VBN decided) (S (VP (TO to) (VP (VB postone) (NP (NP (NN development)) (PP (IN of) (NP (NP (DT a) (ADJP (QP (CD five) (CD billion))) (NN dlr)) (NP (NP (JJ hydroelectric) (NN power) (NN project)) (PP (IN in) (NP (NP (NNP Sarawak)) (, ,) (NP (NNP East) (NNP Malaysia)) (, ,))))))) (SBAR (IN until) (S (NP (DT the) (NN economy)) (VP (VP (VBZ improves)) (, ,) (NP (NP (NN deputy) (NNP Minister)) (PP (IN of) (NP (NNP Energy))))))))))))) (, ,) (NP (NP (NNP Telecoms) (CC and) (NNP Post)) (NNP Zainal) (NNP Abidin) (NNP Zin)) (VP (VBD said)) (. .))) </parse>
        <dependencies type="basic-dependencies">
          <dep type="root">
            <governor idx="0">ROOT</governor>
            <dependent idx="37">said</dependent>
          </dep>
          <dep type="nsubj">
            <governor idx="3">decided</governor>
            <dependent idx="1">Malaysia</dependent>
          </dep>
          <dep type="aux">
            <governor idx="3">decided</governor>
            <dependent idx="2">has</dependent>
          </dep>
          <dep type="ccomp">
            <governor idx="37">said</governor>
            <dependent idx="3">decided</dependent>
          </dep>
          <dep type="aux">
            <governor idx="5">postone</governor>
            <dependent idx="4">to</dependent>
          </dep>
          <dep type="xcomp">
            <governor idx="3">decided</governor>
            <dependent idx="5">postone</dependent>
          </dep>
          <dep type="dobj">
            <governor idx="5">postone</governor>
            <dependent idx="6">development</dependent>
          </dep>
          <dep type="prep">
            <governor idx="6">development</governor>
            <dependent idx="7">of</dependent>
          </dep>
          <dep type="det">
            <governor idx="11">dlr</governor>
            <dependent idx="8">a</dependent>
          </dep>
          <dep type="number">
            <governor idx="10">billion</governor>
            <dependent idx="9">five</dependent>
          </dep>
          <dep type="num">
            <governor idx="11">dlr</governor>
            <dependent idx="10">billion</dependent>
          </dep>
          <dep type="pobj">
            <governor idx="7">of</governor>
            <dependent idx="11">dlr</dependent>
          </dep>
          <dep type="amod">
            <governor idx="14">project</governor>
            <dependent idx="12">hydroelectric</dependent>
          </dep>
          <dep type="nn">
            <governor idx="14">project</governor>
            <dependent idx="13">power</dependent>
          </dep>
          <dep type="dep">
            <governor idx="11">dlr</governor>
            <dependent idx="14">project</dependent>
          </dep>
          <dep type="prep">
            <governor idx="14">project</governor>
            <dependent idx="15">in</dependent>
          </dep>
          <dep type="pobj">
            <governor idx="15">in</governor>
            <dependent idx="16">Sarawak</dependent>
          </dep>
          <dep type="nn">
            <governor idx="19">Malaysia</governor>
            <dependent idx="18">East</dependent>
          </dep>
          <dep type="appos">
            <governor idx="16">Sarawak</governor>
            <dependent idx="19">Malaysia</dependent>
          </dep>
          <dep type="mark">
            <governor idx="24">improves</governor>
            <dependent idx="21">until</dependent>
          </dep>
          <dep type="det">
            <governor idx="23">economy</governor>
            <dependent idx="22">the</dependent>
          </dep>
          <dep type="nsubj">
            <governor idx="24">improves</governor>
            <dependent idx="23">economy</dependent>
          </dep>
          <dep type="advcl">
            <governor idx="5">postone</governor>
            <dependent idx="24">improves</dependent>
          </dep>
          <dep type="nn">
            <governor idx="27">Minister</governor>
            <dependent idx="26">deputy</dependent>
          </dep>
          <dep type="dobj">
            <governor idx="24">improves</governor>
            <dependent idx="27">Minister</dependent>
          </dep>
          <dep type="prep">
            <governor idx="27">Minister</governor>
            <dependent idx="28">of</dependent>
          </dep>
          <dep type="pobj">
            <governor idx="28">of</governor>
            <dependent idx="29">Energy</dependent>
          </dep>
          <dep type="nn">
            <governor idx="36">Zin</governor>
            <dependent idx="31">Telecoms</dependent>
          </dep>
          <dep type="cc">
            <governor idx="31">Telecoms</governor>
            <dependent idx="32">and</dependent>
          </dep>
          <dep type="conj">
            <governor idx="31">Telecoms</governor>
            <dependent idx="33">Post</dependent>
          </dep>
          <dep type="nn">
            <governor idx="36">Zin</governor>
            <dependent idx="34">Zainal</dependent>
          </dep>
          <dep type="nn">
            <governor idx="36">Zin</governor>
            <dependent idx="35">Abidin</dependent>
          </dep>
          <dep type="nsubj">
            <governor idx="37">said</governor>
            <dependent idx="36">Zin</dependent>
          </dep>
        </dependencies>
        <dependencies type="collapsed-dependencies">
          <dep type="root">
            <governor idx="0">ROOT</governor>
            <dependent idx="37">said</dependent>
          </dep>
          <dep type="nsubj">
            <governor idx="3">decided</governor>
            <dependent idx="1">Malaysia</dependent>
          </dep>
          <dep type="aux">
            <governor idx="3">decided</governor>
            <dependent idx="2">has</dependent>
          </dep>
          <dep type="ccomp">
            <governor idx="37">said</governor>
            <dependent idx="3">decided</dependent>
          </dep>
          <dep type="aux">
            <governor idx="5">postone</governor>
            <dependent idx="4">to</dependent>
          </dep>
          <dep type="xcomp">
            <governor idx="3">decided</governor>
            <dependent idx="5">postone</dependent>
          </dep>
          <dep type="dobj">
            <governor idx="5">postone</governor>
            <dependent idx="6">development</dependent>
          </dep>
          <dep type="det">
            <governor idx="11">dlr</governor>
            <dependent idx="8">a</dependent>
          </dep>
          <dep type="number">
            <governor idx="10">billion</governor>
            <dependent idx="9">five</dependent>
          </dep>
          <dep type="num">
            <governor idx="11">dlr</governor>
            <dependent idx="10">billion</dependent>
          </dep>
          <dep type="prep_of">
            <governor idx="6">development</governor>
            <dependent idx="11">dlr</dependent>
          </dep>
          <dep type="amod">
            <governor idx="14">project</governor>
            <dependent idx="12">hydroelectric</dependent>
          </dep>
          <dep type="nn">
            <governor idx="14">project</governor>
            <dependent idx="13">power</dependent>
          </dep>
          <dep type="dep">
            <governor idx="11">dlr</governor>
            <dependent idx="14">project</dependent>
          </dep>
          <dep type="prep_in">
            <governor idx="14">project</governor>
            <dependent idx="16">Sarawak</dependent>
          </dep>
          <dep type="nn">
            <governor idx="19">Malaysia</governor>
            <dependent idx="18">East</dependent>
          </dep>
          <dep type="appos">
            <governor idx="16">Sarawak</governor>
            <dependent idx="19">Malaysia</dependent>
          </dep>
          <dep type="mark">
            <governor idx="24">improves</governor>
            <dependent idx="21">until</dependent>
          </dep>
          <dep type="det">
            <governor idx="23">economy</governor>
            <dependent idx="22">the</dependent>
          </dep>
          <dep type="nsubj">
            <governor idx="24">improves</governor>
            <dependent idx="23">economy</dependent>
          </dep>
          <dep type="advcl">
            <governor idx="5">postone</governor>
            <dependent idx="24">improves</dependent>
          </dep>
          <dep type="nn">
            <governor idx="27">Minister</governor>
            <dependent idx="26">deputy</dependent>
          </dep>
          <dep type="dobj">
            <governor idx="24">improves</governor>
            <dependent idx="27">Minister</dependent>
          </dep>
          <dep type="prep_of">
            <governor idx="27">Minister</governor>
            <dependent idx="29">Energy</dependent>
          </dep>
          <dep type="nn">
            <governor idx="36">Zin</governor>
            <dependent idx="31">Telecoms</dependent>
          </dep>
          <dep type="conj_and">
            <governor idx="31">Telecoms</governor>
            <dependent idx="33">Post</dependent>
          </dep>
          <dep type="nn">
            <governor idx="36">Zin</governor>
            <dependent idx="34">Zainal</dependent>
          </dep>
          <dep type="nn">
            <governor idx="36">Zin</governor>
            <dependent idx="35">Abidin</dependent>
          </dep>
          <dep type="nsubj">
            <governor idx="37">said</governor>
            <dependent idx="36">Zin</dependent>
          </dep>
        </dependencies>
        <dependencies type="collapsed-ccprocessed-dependencies">
          <dep type="root">
            <governor idx="0">ROOT</governor>
            <dependent idx="37">said</dependent>
          </dep>
          <dep type="nsubj">
            <governor idx="3">decided</governor>
            <dependent idx="1">Malaysia</dependent>
          </dep>
          <dep type="aux">
            <governor idx="3">decided</governor>
            <dependent idx="2">has</dependent>
          </dep>
          <dep type="ccomp">
            <governor idx="37">said</governor>
            <dependent idx="3">decided</dependent>
          </dep>
          <dep type="aux">
            <governor idx="5">postone</governor>
            <dependent idx="4">to</dependent>
          </dep>
          <dep type="xcomp">
            <governor idx="3">decided</governor>
            <dependent idx="5">postone</dependent>
          </dep>
          <dep type="dobj">
            <governor idx="5">postone</governor>
            <dependent idx="6">development</dependent>
          </dep>
          <dep type="det">
            <governor idx="11">dlr</governor>
            <dependent idx="8">a</dependent>
          </dep>
          <dep type="number">
            <governor idx="10">billion</governor>
            <dependent idx="9">five</dependent>
          </dep>
          <dep type="num">
            <governor idx="11">dlr</governor>
            <dependent idx="10">billion</dependent>
          </dep>
          <dep type="prep_of">
            <governor idx="6">development</governor>
            <dependent idx="11">dlr</dependent>
          </dep>
          <dep type="amod">
            <governor idx="14">project</governor>
            <dependent idx="12">hydroelectric</dependent>
          </dep>
          <dep type="nn">
            <governor idx="14">project</governor>
            <dependent idx="13">power</dependent>
          </dep>
          <dep type="dep">
            <governor idx="11">dlr</governor>
            <dependent idx="14">project</dependent>
          </dep>
          <dep type="prep_in">
            <governor idx="14">project</governor>
            <dependent idx="16">Sarawak</dependent>
          </dep>
          <dep type="nn">
            <governor idx="19">Malaysia</governor>
            <dependent idx="18">East</dependent>
          </dep>
          <dep type="appos">
            <governor idx="16">Sarawak</governor>
            <dependent idx="19">Malaysia</dependent>
          </dep>
          <dep type="mark">
            <governor idx="24">improves</governor>
            <dependent idx="21">until</dependent>
          </dep>
          <dep type="det">
            <governor idx="23">economy</governor>
            <dependent idx="22">the</dependent>
          </dep>
          <dep type="nsubj">
            <governor idx="24">improves</governor>
            <dependent idx="23">economy</dependent>
          </dep>
          <dep type="advcl">
            <governor idx="5">postone</governor>
            <dependent idx="24">improves</dependent>
          </dep>
          <dep type="nn">
            <governor idx="27">Minister</governor>
            <dependent idx="26">deputy</dependent>
          </dep>
          <dep type="dobj">
            <governor idx="24">improves</governor>
            <dependent idx="27">Minister</dependent>
          </dep>
          <dep type="prep_of">
            <governor idx="27">Minister</governor>
            <dependent idx="29">Energy</dependent>
          </dep>
          <dep type="nn">
            <governor idx="36">Zin</governor>
            <dependent idx="31">Telecoms</dependent>
          </dep>
          <dep type="conj_and">
            <governor idx="31">Telecoms</governor>
            <dependent idx="33">Post</dependent>
          </dep>
          <dep type="nn">
            <governor idx="36">Zin</governor>
            <dependent idx="33">Post</dependent>
          </dep>
          <dep type="nn">
            <governor idx="36">Zin</governor>
            <dependent idx="34">Zainal</dependent>
          </dep>
          <dep type="nn">
            <governor idx="36">Zin</governor>
            <dependent idx="35">Abidin</dependent>
          </dep>
          <dep type="nsubj">
            <governor idx="37">said</governor>
            <dependent idx="36">Zin</dependent>
          </dep>
        </dependencies>
      </sentence>
      <sentence id="2">
        <tokens>
          <token id="1">
            <word>He</word>
            <lemma>he</lemma>
            <CharacterOffsetBegin>218</CharacterOffsetBegin>
            <CharacterOffsetEnd>220</CharacterOffsetEnd>
            <POS>PRP</POS>
          </token>
          <token id="2">
            <word>told</word>
            <lemma>tell</lemma>
            <CharacterOffsetBegin>221</CharacterOffsetBegin>
            <CharacterOffsetEnd>225</CharacterOffsetEnd>
            <POS>VBD</POS>
          </token>
          <token id="3">
            <word>reporters</word>
            <lemma>reporter</lemma>
            <CharacterOffsetBegin>226</CharacterOffsetBegin>
            <CharacterOffsetEnd>235</CharacterOffsetEnd>
            <POS>NNS</POS>
          </token>
          <token id="4">
            <word>a</word>
            <lemma>a</lemma>
            <CharacterOffsetBegin>236</CharacterOffsetBegin>
            <CharacterOffsetEnd>237</CharacterOffsetEnd>
            <POS>DT</POS>
          </token>
          <token id="5">
            <word>shortage</word>
            <lemma>shortage</lemma>
            <CharacterOffsetBegin>238</CharacterOffsetBegin>
            <CharacterOffsetEnd>246</CharacterOffsetEnd>
            <POS>NN</POS>
          </token>
          <token id="6">
            <word>of</word>
            <lemma>of</lemma>
            <CharacterOffsetBegin>247</CharacterOffsetBegin>
            <CharacterOffsetEnd>249</CharacterOffsetEnd>
            <POS>IN</POS>
          </token>
          <token id="7">
            <word>funds</word>
            <lemma>fund</lemma>
            <CharacterOffsetBegin>250</CharacterOffsetBegin>
            <CharacterOffsetEnd>255</CharacterOffsetEnd>
            <POS>NNS</POS>
          </token>
          <token id="8">
            <word>forced</word>
            <lemma>force</lemma>
            <CharacterOffsetBegin>256</CharacterOffsetBegin>
            <CharacterOffsetEnd>262</CharacterOffsetEnd>
            <POS>VBD</POS>
          </token>
          <token id="9">
            <word>the</word>
            <lemma>the</lemma>
            <CharacterOffsetBegin>263</CharacterOffsetBegin>
            <CharacterOffsetEnd>266</CharacterOffsetEnd>
            <POS>DT</POS>
          </token>
          <token id="10">
            <word>government</word>
            <lemma>government</lemma>
            <CharacterOffsetBegin>267</CharacterOffsetBegin>
            <CharacterOffsetEnd>277</CharacterOffsetEnd>
            <POS>NN</POS>
          </token>
          <token id="11">
            <word>to</word>
            <lemma>to</lemma>
            <CharacterOffsetBegin>278</CharacterOffsetBegin>
            <CharacterOffsetEnd>280</CharacterOffsetEnd>
            <POS>TO</POS>
          </token>
          <token id="12">
            <word>shelve</word>
            <lemma>shelve</lemma>
            <CharacterOffsetBegin>281</CharacterOffsetBegin>
            <CharacterOffsetEnd>287</CharacterOffsetEnd>
            <POS>VB</POS>
          </token>
          <token id="13">
            <word>the</word>
            <lemma>the</lemma>
            <CharacterOffsetBegin>288</CharacterOffsetBegin>
            <CharacterOffsetEnd>291</CharacterOffsetEnd>
            <POS>DT</POS>
          </token>
          <token id="14">
            <word>project</word>
            <lemma>project</lemma>
            <CharacterOffsetBegin>292</CharacterOffsetBegin>
            <CharacterOffsetEnd>299</CharacterOffsetEnd>
            <POS>NN</POS>
          </token>
          <token id="15">
            <word>,</word>
            <lemma>,</lemma>
            <CharacterOffsetBegin>299</CharacterOffsetBegin>
            <CharacterOffsetEnd>300</CharacterOffsetEnd>
            <POS>,</POS>
          </token>
          <token id="16">
            <word>which</word>
            <lemma>which</lemma>
            <CharacterOffsetBegin>301</CharacterOffsetBegin>
            <CharacterOffsetEnd>306</CharacterOffsetEnd>
            <POS>WDT</POS>
          </token>
          <token id="17">
            <word>involved</word>
            <lemma>involve</lemma>
            <CharacterOffsetBegin>307</CharacterOffsetBegin>
            <CharacterOffsetEnd>315</CharacterOffsetEnd>
            <POS>VBD</POS>
          </token>
          <token id="18">
            <word>building</word>
            <lemma>build</lemma>
            <CharacterOffsetBegin>316</CharacterOffsetBegin>
            <CharacterOffsetEnd>324</CharacterOffsetEnd>
            <POS>VBG</POS>
          </token>
          <token id="19">
            <word>several</word>
            <lemma>several</lemma>
            <CharacterOffsetBegin>325</CharacterOffsetBegin>
            <CharacterOffsetEnd>332</CharacterOffsetEnd>
            <POS>JJ</POS>
          </token>
          <token id="20">
            <word>dams</word>
            <lemma>dam</lemma>
            <CharacterOffsetBegin>333</CharacterOffsetBegin>
            <CharacterOffsetEnd>337</CharacterOffsetEnd>
            <POS>NNS</POS>
          </token>
          <token id="21">
            <word>and</word>
            <lemma>and</lemma>
            <CharacterOffsetBegin>338</CharacterOffsetBegin>
            <CharacterOffsetEnd>341</CharacterOffsetEnd>
            <POS>CC</POS>
          </token>
          <token id="22">
            <word>a</word>
            <lemma>a</lemma>
            <CharacterOffsetBegin>342</CharacterOffsetBegin>
            <CharacterOffsetEnd>343</CharacterOffsetEnd>
            <POS>DT</POS>
          </token>
          <token id="23">
            <word>20,000</word>
            <lemma>20,000</lemma>
            <CharacterOffsetBegin>344</CharacterOffsetBegin>
            <CharacterOffsetEnd>350</CharacterOffsetEnd>
            <POS>CD</POS>
          </token>
          <token id="24">
            <word>megawatt</word>
            <lemma>megawatt</lemma>
            <CharacterOffsetBegin>351</CharacterOffsetBegin>
            <CharacterOffsetEnd>359</CharacterOffsetEnd>
            <POS>NN</POS>
          </token>
          <token id="25">
            <word>capacity</word>
            <lemma>capacity</lemma>
            <CharacterOffsetBegin>360</CharacterOffsetBegin>
            <CharacterOffsetEnd>368</CharacterOffsetEnd>
            <POS>NN</POS>
          </token>
          <token id="26">
            <word>undersea</word>
            <lemma>undersea</lemma>
            <CharacterOffsetBegin>369</CharacterOffsetBegin>
            <CharacterOffsetEnd>377</CharacterOffsetEnd>
            <POS>NN</POS>
          </token>
          <token id="27">
            <word>cable</word>
            <lemma>cable</lemma>
            <CharacterOffsetBegin>378</CharacterOffsetBegin>
            <CharacterOffsetEnd>383</CharacterOffsetEnd>
            <POS>NN</POS>
          </token>
          <token id="28">
            <word>.</word>
            <lemma>.</lemma>
            <CharacterOffsetBegin>383</CharacterOffsetBegin>
            <CharacterOffsetEnd>384</CharacterOffsetEnd>
            <POS>.</POS>
          </token>
        </tokens>
        <parse>(ROOT (S (NP (PRP He)) (VP (VBD told) (NP (NP (NNS reporters)) (SBAR (S (NP (NP (DT a) (NN shortage)) (PP (IN of) (NP (NNS funds)))) (VP (VBD forced) (NP (DT the) (NN government) (S (VP (TO to) (VP (VB shelve) (NP (NP (DT the) (NN project)) (, ,) (SBAR (WHNP (WDT which)) (S (VP (VBD involved) (S (VP (VBG building) (NP (NP (JJ several) (NNS dams)) (CC and) (NP (DT a) (ADJP (CD 20,000) (NN megawatt)) (NN capacity) (NN undersea) (NN cable)))))))))))))))))) (. .))) </parse>
        <dependencies type="basic-dependencies">
          <dep type="root">
            <governor idx="0">ROOT</governor>
            <dependent idx="2">told</dependent>
          </dep>
          <dep type="nsubj">
            <governor idx="2">told</governor>
            <dependent idx="1">He</dependent>
          </dep>
          <dep type="dobj">
            <governor idx="2">told</governor>
            <dependent idx="3">reporters</dependent>
          </dep>
          <dep type="det">
            <governor idx="5">shortage</governor>
            <dependent idx="4">a</dependent>
          </dep>
          <dep type="nsubj">
            <governor idx="8">forced</governor>
            <dependent idx="5">shortage</dependent>
          </dep>
          <dep type="prep">
            <governor idx="5">shortage</governor>
            <dependent idx="6">of</dependent>
          </dep>
          <dep type="pobj">
            <governor idx="6">of</governor>
            <dependent idx="7">funds</dependent>
          </dep>
          <dep type="rcmod">
            <governor idx="3">reporters</governor>
            <dependent idx="8">forced</dependent>
          </dep>
          <dep type="det">
            <governor idx="10">government</governor>
            <dependent idx="9">the</dependent>
          </dep>
          <dep type="dobj">
            <governor idx="8">forced</governor>
            <dependent idx="10">government</dependent>
          </dep>
          <dep type="aux">
            <governor idx="12">shelve</governor>
            <dependent idx="11">to</dependent>
          </dep>
          <dep type="vmod">
            <governor idx="10">government</governor>
            <dependent idx="12">shelve</dependent>
          </dep>
          <dep type="det">
            <governor idx="14">project</governor>
            <dependent idx="13">the</dependent>
          </dep>
          <dep type="dobj">
            <governor idx="12">shelve</governor>
            <dependent idx="14">project</dependent>
          </dep>
          <dep type="nsubj">
            <governor idx="17">involved</governor>
            <dependent idx="16">which</dependent>
          </dep>
          <dep type="rcmod">
            <governor idx="14">project</governor>
            <dependent idx="17">involved</dependent>
          </dep>
          <dep type="xcomp">
            <governor idx="17">involved</governor>
            <dependent idx="18">building</dependent>
          </dep>
          <dep type="amod">
            <governor idx="20">dams</governor>
            <dependent idx="19">several</dependent>
          </dep>
          <dep type="dobj">
            <governor idx="18">building</governor>
            <dependent idx="20">dams</dependent>
          </dep>
          <dep type="cc">
            <governor idx="20">dams</governor>
            <dependent idx="21">and</dependent>
          </dep>
          <dep type="det">
            <governor idx="27">cable</governor>
            <dependent idx="22">a</dependent>
          </dep>
          <dep type="number">
            <governor idx="24">megawatt</governor>
            <dependent idx="23">20,000</dependent>
          </dep>
          <dep type="amod">
            <governor idx="27">cable</governor>
            <dependent idx="24">megawatt</dependent>
          </dep>
          <dep type="nn">
            <governor idx="27">cable</governor>
            <dependent idx="25">capacity</dependent>
          </dep>
          <dep type="nn">
            <governor idx="27">cable</governor>
            <dependent idx="26">undersea</dependent>
          </dep>
          <dep type="conj">
            <governor idx="20">dams</governor>
            <dependent idx="27">cable</dependent>
          </dep>
        </dependencies>
        <dependencies type="collapsed-dependencies">
          <dep type="root">
            <governor idx="0">ROOT</governor>
            <dependent idx="2">told</dependent>
          </dep>
          <dep type="nsubj">
            <governor idx="2">told</governor>
            <dependent idx="1">He</dependent>
          </dep>
          <dep type="dobj">
            <governor idx="2">told</governor>
            <dependent idx="3">reporters</dependent>
          </dep>
          <dep type="det">
            <governor idx="5">shortage</governor>
            <dependent idx="4">a</dependent>
          </dep>
          <dep type="nsubj">
            <governor idx="8">forced</governor>
            <dependent idx="5">shortage</dependent>
          </dep>
          <dep type="prep_of">
            <governor idx="5">shortage</governor>
            <dependent idx="7">funds</dependent>
          </dep>
          <dep type="rcmod">
            <governor idx="3">reporters</governor>
            <dependent idx="8">forced</dependent>
          </dep>
          <dep type="det">
            <governor idx="10">government</governor>
            <dependent idx="9">the</dependent>
          </dep>
          <dep type="dobj">
            <governor idx="8">forced</governor>
            <dependent idx="10">government</dependent>
          </dep>
          <dep type="aux">
            <governor idx="12">shelve</governor>
            <dependent idx="11">to</dependent>
          </dep>
          <dep type="vmod">
            <governor idx="10">government</governor>
            <dependent idx="12">shelve</dependent>
          </dep>
          <dep type="det">
            <governor idx="14">project</governor>
            <dependent idx="13">the</dependent>
          </dep>
          <dep type="dobj">
            <governor idx="12">shelve</governor>
            <dependent idx="14">project</dependent>
          </dep>
          <dep type="nsubj">
            <governor idx="17">involved</governor>
            <dependent idx="16">which</dependent>
          </dep>
          <dep type="rcmod">
            <governor idx="14">project</governor>
            <dependent idx="17">involved</dependent>
          </dep>
          <dep type="xcomp">
            <governor idx="17">involved</governor>
            <dependent idx="18">building</dependent>
          </dep>
          <dep type="amod">
            <governor idx="20">dams</governor>
            <dependent idx="19">several</dependent>
          </dep>
          <dep type="dobj">
            <governor idx="18">building</governor>
            <dependent idx="20">dams</dependent>
          </dep>
          <dep type="det">
            <governor idx="27">cable</governor>
            <dependent idx="22">a</dependent>
          </dep>
          <dep type="number">
            <governor idx="24">megawatt</governor>
            <dependent idx="23">20,000</dependent>
          </dep>
          <dep type="amod">
            <governor idx="27">cable</governor>
            <dependent idx="24">megawatt</dependent>
          </dep>
          <dep type="nn">
            <governor idx="27">cable</governor>
            <dependent idx="25">capacity</dependent>
          </dep>
          <dep type="nn">
            <governor idx="27">cable</governor>
            <dependent idx="26">undersea</dependent>
          </dep>
          <dep type="conj_and">
            <governor idx="20">dams</governor>
            <dependent idx="27">cable</dependent>
          </dep>
        </dependencies>
        <dependencies type="collapsed-ccprocessed-dependencies">
          <dep type="root">
            <governor idx="0">ROOT</governor>
            <dependent idx="2">told</dependent>
          </dep>
          <dep type="nsubj">
            <governor idx="2">told</governor>
            <dependent idx="1">He</dependent>
          </dep>
          <dep type="dobj">
            <governor idx="2">told</governor>
            <dependent idx="3">reporters</dependent>
          </dep>
          <dep type="det">
            <governor idx="5">shortage</governor>
            <dependent idx="4">a</dependent>
          </dep>
          <dep type="nsubj">
            <governor idx="8">forced</governor>
            <dependent idx="5">shortage</dependent>
          </dep>
          <dep type="prep_of">
            <governor idx="5">shortage</governor>
            <dependent idx="7">funds</dependent>
          </dep>
          <dep type="rcmod">
            <governor idx="3">reporters</governor>
            <dependent idx="8">forced</dependent>
          </dep>
          <dep type="det">
            <governor idx="10">government</governor>
            <dependent idx="9">the</dependent>
          </dep>
          <dep type="dobj">
            <governor idx="8">forced</governor>
            <dependent idx="10">government</dependent>
          </dep>
          <dep type="aux">
            <governor idx="12">shelve</governor>
            <dependent idx="11">to</dependent>
          </dep>
          <dep type="vmod">
            <governor idx="10">government</governor>
            <dependent idx="12">shelve</dependent>
          </dep>
          <dep type="det">
            <governor idx="14">project</governor>
            <dependent idx="13">the</dependent>
          </dep>
          <dep type="dobj">
            <governor idx="12">shelve</governor>
            <dependent idx="14">project</dependent>
          </dep>
          <dep type="nsubj">
            <governor idx="17">involved</governor>
            <dependent idx="16">which</dependent>
          </dep>
          <dep type="rcmod">
            <governor idx="14">project</governor>
            <dependent idx="17">involved</dependent>
          </dep>
          <dep type="xcomp">
            <governor idx="17">involved</governor>
            <dependent idx="18">building</dependent>
          </dep>
          <dep type="amod">
            <governor idx="20">dams</governor>
            <dependent idx="19">several</dependent>
          </dep>
          <dep type="dobj">
            <governor idx="18">building</governor>
            <dependent idx="20">dams</dependent>
          </dep>
          <dep type="det">
            <governor idx="27">cable</governor>
            <dependent idx="22">a</dependent>
          </dep>
          <dep type="number">
            <governor idx="24">megawatt</governor>
            <dependent idx="23">20,000</dependent>
          </dep>
          <dep type="amod">
            <governor idx="27">cable</governor>
            <dependent idx="24">megawatt</dependent>
          </dep>
          <dep type="nn">
            <governor idx="27">cable</governor>
            <dependent idx="25">capacity</dependent>
          </dep>
          <dep type="nn">
            <governor idx="27">cable</governor>
            <dependent idx="26">undersea</dependent>
          </dep>
          <dep type="dobj">
            <governor idx="18">building</governor>
            <dependent idx="27">cable</dependent>
          </dep>
          <dep type="conj_and">
            <governor idx="20">dams</governor>
            <dependent idx="27">cable</dependent>
          </dep>
        </dependencies>
      </sentence>
      <sentence id="3">
        <tokens>
          <token id="1">
            <word>Malaysia</word>
            <lemma>Malaysia</lemma>
            <CharacterOffsetBegin>385</CharacterOffsetBegin>
            <CharacterOffsetEnd>393</CharacterOffsetEnd>
            <POS>NNP</POS>
          </token>
          <token id="2">
            <word>originally</word>
            <lemma>originally</lemma>
            <CharacterOffsetBegin>394</CharacterOffsetBegin>
            <CharacterOffsetEnd>404</CharacterOffsetEnd>
            <POS>RB</POS>
          </token>
          <token id="3">
            <word>planned</word>
            <lemma>plan</lemma>
            <CharacterOffsetBegin>405</CharacterOffsetBegin>
            <CharacterOffsetEnd>412</CharacterOffsetEnd>
            <POS>VBD</POS>
          </token>
          <token id="4">
            <word>to</word>
            <lemma>to</lemma>
            <CharacterOffsetBegin>413</CharacterOffsetBegin>
            <CharacterOffsetEnd>415</CharacterOffsetEnd>
            <POS>TO</POS>
          </token>
          <token id="5">
            <word>export</word>
            <lemma>export</lemma>
            <CharacterOffsetBegin>416</CharacterOffsetBegin>
            <CharacterOffsetEnd>422</CharacterOffsetEnd>
            <POS>VB</POS>
          </token>
          <token id="6">
            <word>electricity</word>
            <lemma>electricity</lemma>
            <CharacterOffsetBegin>423</CharacterOffsetBegin>
            <CharacterOffsetEnd>434</CharacterOffsetEnd>
            <POS>NN</POS>
          </token>
          <token id="7">
            <word>generated</word>
            <lemma>generate</lemma>
            <CharacterOffsetBegin>435</CharacterOffsetBegin>
            <CharacterOffsetEnd>444</CharacterOffsetEnd>
            <POS>VBN</POS>
          </token>
          <token id="8">
            <word>by</word>
            <lemma>by</lemma>
            <CharacterOffsetBegin>445</CharacterOffsetBegin>
            <CharacterOffsetEnd>447</CharacterOffsetEnd>
            <POS>IN</POS>
          </token>
          <token id="9">
            <word>the</word>
            <lemma>the</lemma>
            <CharacterOffsetBegin>448</CharacterOffsetBegin>
            <CharacterOffsetEnd>451</CharacterOffsetEnd>
            <POS>DT</POS>
          </token>
          <token id="10">
            <word>project</word>
            <lemma>project</lemma>
            <CharacterOffsetBegin>452</CharacterOffsetBegin>
            <CharacterOffsetEnd>459</CharacterOffsetEnd>
            <POS>NN</POS>
          </token>
          <token id="11">
            <word>to</word>
            <lemma>to</lemma>
            <CharacterOffsetBegin>460</CharacterOffsetBegin>
            <CharacterOffsetEnd>462</CharacterOffsetEnd>
            <POS>TO</POS>
          </token>
          <token id="12">
            <word>Singapore</word>
            <lemma>Singapore</lemma>
            <CharacterOffsetBegin>463</CharacterOffsetBegin>
            <CharacterOffsetEnd>472</CharacterOffsetEnd>
            <POS>NNP</POS>
          </token>
          <token id="13">
            <word>,</word>
            <lemma>,</lemma>
            <CharacterOffsetBegin>472</CharacterOffsetBegin>
            <CharacterOffsetEnd>473</CharacterOffsetEnd>
            <POS>,</POS>
          </token>
          <token id="14">
            <word>Brunei</word>
            <lemma>Brunei</lemma>
            <CharacterOffsetBegin>474</CharacterOffsetBegin>
            <CharacterOffsetEnd>480</CharacterOffsetEnd>
            <POS>NNP</POS>
          </token>
          <token id="15">
            <word>and</word>
            <lemma>and</lemma>
            <CharacterOffsetBegin>481</CharacterOffsetBegin>
            <CharacterOffsetEnd>484</CharacterOffsetEnd>
            <POS>CC</POS>
          </token>
          <token id="16">
            <word>Indonesia</word>
            <lemma>Indonesia</lemma>
            <CharacterOffsetBegin>485</CharacterOffsetBegin>
            <CharacterOffsetEnd>494</CharacterOffsetEnd>
            <POS>NNP</POS>
          </token>
          <token id="17">
            <word>by</word>
            <lemma>by</lemma>
            <CharacterOffsetBegin>495</CharacterOffsetBegin>
            <CharacterOffsetEnd>497</CharacterOffsetEnd>
            <POS>IN</POS>
          </token>
          <token id="18">
            <word>2000</word>
            <lemma>2000</lemma>
            <CharacterOffsetBegin>498</CharacterOffsetBegin>
            <CharacterOffsetEnd>502</CharacterOffsetEnd>
            <POS>CD</POS>
          </token>
          <token id="19">
            <word>if</word>
            <lemma>if</lemma>
            <CharacterOffsetBegin>503</CharacterOffsetBegin>
            <CharacterOffsetEnd>505</CharacterOffsetEnd>
            <POS>IN</POS>
          </token>
          <token id="20">
            <word>the</word>
            <lemma>the</lemma>
            <CharacterOffsetBegin>506</CharacterOffsetBegin>
            <CharacterOffsetEnd>509</CharacterOffsetEnd>
            <POS>DT</POS>
          </token>
          <token id="21">
            <word>project</word>
            <lemma>project</lemma>
            <CharacterOffsetBegin>510</CharacterOffsetBegin>
            <CharacterOffsetEnd>517</CharacterOffsetEnd>
            <POS>NN</POS>
          </token>
          <token id="22">
            <word>could</word>
            <lemma>could</lemma>
            <CharacterOffsetBegin>518</CharacterOffsetBegin>
            <CharacterOffsetEnd>523</CharacterOffsetEnd>
            <POS>MD</POS>
          </token>
          <token id="23">
            <word>be</word>
            <lemma>be</lemma>
            <CharacterOffsetBegin>524</CharacterOffsetBegin>
            <CharacterOffsetEnd>526</CharacterOffsetEnd>
            <POS>VB</POS>
          </token>
          <token id="24">
            <word>started</word>
            <lemma>start</lemma>
            <CharacterOffsetBegin>527</CharacterOffsetBegin>
            <CharacterOffsetEnd>534</CharacterOffsetEnd>
            <POS>VBN</POS>
          </token>
          <token id="25">
            <word>before</word>
            <lemma>before</lemma>
            <CharacterOffsetBegin>535</CharacterOffsetBegin>
            <CharacterOffsetEnd>541</CharacterOffsetEnd>
            <POS>IN</POS>
          </token>
          <token id="26">
            <word>1996</word>
            <lemma>1996</lemma>
            <CharacterOffsetBegin>542</CharacterOffsetBegin>
            <CharacterOffsetEnd>546</CharacterOffsetEnd>
            <POS>CD</POS>
          </token>
          <token id="27">
            <word>,</word>
            <lemma>,</lemma>
            <CharacterOffsetBegin>546</CharacterOffsetBegin>
            <CharacterOffsetEnd>547</CharacterOffsetEnd>
            <POS>,</POS>
          </token>
          <token id="28">
            <word>Zainal</word>
            <lemma>Zainal</lemma>
            <CharacterOffsetBegin>548</CharacterOffsetBegin>
            <CharacterOffsetEnd>554</CharacterOffsetEnd>
            <POS>NNP</POS>
          </token>
          <token id="29">
            <word>said</word>
            <lemma>say</lemma>
            <CharacterOffsetBegin>555</CharacterOffsetBegin>
            <CharacterOffsetEnd>559</CharacterOffsetEnd>
            <POS>VBD</POS>
          </token>
          <token id="30">
            <word>.</word>
            <lemma>.</lemma>
            <CharacterOffsetBegin>559</CharacterOffsetBegin>
            <CharacterOffsetEnd>560</CharacterOffsetEnd>
            <POS>.</POS>
          </token>
        </tokens>
        <parse>(ROOT (S (S (NP (NNP Malaysia)) (ADVP (RB originally)) (VP (VBD planned) (S (VP (TO to) (VP (VB export) (NP (NP (NN electricity)) (VP (VBN generated) (PP (IN by) (NP (DT the) (NN project))) (PP (TO to) (NP (NNP Singapore) (, ,) (NNP Brunei) (CC and) (NNP Indonesia))) (PP (IN by) (NP (CD 2000)))))))) (SBAR (IN if) (S (NP (DT the) (NN project)) (VP (MD could) (VP (VB be) (VP (VBN started) (PP (IN before) (NP (CD 1996)))))))))) (, ,) (NP (NNP Zainal)) (VP (VBD said)) (. .))) </parse>
        <dependencies type="basic-dependencies">
          <dep type="root">
            <governor idx="0">ROOT</governor>
            <dependent idx="29">said</dependent>
          </dep>
          <dep type="nsubj">
            <governor idx="3">planned</governor>
            <dependent idx="1">Malaysia</dependent>
          </dep>
          <dep type="advmod">
            <governor idx="3">planned</governor>
            <dependent idx="2">originally</dependent>
          </dep>
          <dep type="ccomp">
            <governor idx="29">said</governor>
            <dependent idx="3">planned</dependent>
          </dep>
          <dep type="aux">
            <governor idx="5">export</governor>
            <dependent idx="4">to</dependent>
          </dep>
          <dep type="xcomp">
            <governor idx="3">planned</governor>
            <dependent idx="5">export</dependent>
          </dep>
          <dep type="dobj">
            <governor idx="5">export</governor>
            <dependent idx="6">electricity</dependent>
          </dep>
          <dep type="vmod">
            <governor idx="6">electricity</governor>
            <dependent idx="7">generated</dependent>
          </dep>
          <dep type="prep">
            <governor idx="7">generated</governor>
            <dependent idx="8">by</dependent>
          </dep>
          <dep type="det">
            <governor idx="10">project</governor>
            <dependent idx="9">the</dependent>
          </dep>
          <dep type="pobj">
            <governor idx="8">by</governor>
            <dependent idx="10">project</dependent>
          </dep>
          <dep type="prep">
            <governor idx="7">generated</governor>
            <dependent idx="11">to</dependent>
          </dep>
          <dep type="pobj">
            <governor idx="11">to</governor>
            <dependent idx="12">Singapore</dependent>
          </dep>
          <dep type="conj">
            <governor idx="12">Singapore</governor>
            <dependent idx="14">Brunei</dependent>
          </dep>
          <dep type="cc">
            <governor idx="12">Singapore</governor>
            <dependent idx="15">and</dependent>
          </dep>
          <dep type="conj">
            <governor idx="12">Singapore</governor>
            <dependent idx="16">Indonesia</dependent>
          </dep>
          <dep type="prep">
            <governor idx="7">generated</governor>
            <dependent idx="17">by</dependent>
          </dep>
          <dep type="pobj">
            <governor idx="17">by</governor>
            <dependent idx="18">2000</dependent>
          </dep>
          <dep type="mark">
            <governor idx="24">started</governor>
            <dependent idx="19">if</dependent>
          </dep>
          <dep type="det">
            <governor idx="21">project</governor>
            <dependent idx="20">the</dependent>
          </dep>
          <dep type="nsubjpass">
            <governor idx="24">started</governor>
            <dependent idx="21">project</dependent>
          </dep>
          <dep type="aux">
            <governor idx="24">started</governor>
            <dependent idx="22">could</dependent>
          </dep>
          <dep type="auxpass">
            <governor idx="24">started</governor>
            <dependent idx="23">be</dependent>
          </dep>
          <dep type="advcl">
            <governor idx="3">planned</governor>
            <dependent idx="24">started</dependent>
          </dep>
          <dep type="prep">
            <governor idx="24">started</governor>
            <dependent idx="25">before</dependent>
          </dep>
          <dep type="pobj">
            <governor idx="25">before</governor>
            <dependent idx="26">1996</dependent>
          </dep>
          <dep type="nsubj">
            <governor idx="29">said</governor>
            <dependent idx="28">Zainal</dependent>
          </dep>
        </dependencies>
        <dependencies type="collapsed-dependencies">
          <dep type="root">
            <governor idx="0">ROOT</governor>
            <dependent idx="29">said</dependent>
          </dep>
          <dep type="nsubj">
            <governor idx="3">planned</governor>
            <dependent idx="1">Malaysia</dependent>
          </dep>
          <dep type="advmod">
            <governor idx="3">planned</governor>
            <dependent idx="2">originally</dependent>
          </dep>
          <dep type="ccomp">
            <governor idx="29">said</governor>
            <dependent idx="3">planned</dependent>
          </dep>
          <dep type="aux">
            <governor idx="5">export</governor>
            <dependent idx="4">to</dependent>
          </dep>
          <dep type="xcomp">
            <governor idx="3">planned</governor>
            <dependent idx="5">export</dependent>
          </dep>
          <dep type="dobj">
            <governor idx="5">export</governor>
            <dependent idx="6">electricity</dependent>
          </dep>
          <dep type="vmod">
            <governor idx="6">electricity</governor>
            <dependent idx="7">generated</dependent>
          </dep>
          <dep type="det">
            <governor idx="10">project</governor>
            <dependent idx="9">the</dependent>
          </dep>
          <dep type="agent">
            <governor idx="7">generated</governor>
            <dependent idx="10">project</dependent>
          </dep>
          <dep type="prep_to">
            <governor idx="7">generated</governor>
            <dependent idx="12">Singapore</dependent>
          </dep>
          <dep type="conj_and">
            <governor idx="12">Singapore</governor>
            <dependent idx="14">Brunei</dependent>
          </dep>
          <dep type="conj_and">
            <governor idx="12">Singapore</governor>
            <dependent idx="16">Indonesia</dependent>
          </dep>
          <dep type="agent">
            <governor idx="7">generated</governor>
            <dependent idx="18">2000</dependent>
          </dep>
          <dep type="mark">
            <governor idx="24">started</governor>
            <dependent idx="19">if</dependent>
          </dep>
          <dep type="det">
            <governor idx="21">project</governor>
            <dependent idx="20">the</dependent>
          </dep>
          <dep type="nsubjpass">
            <governor idx="24">started</governor>
            <dependent idx="21">project</dependent>
          </dep>
          <dep type="aux">
            <governor idx="24">started</governor>
            <dependent idx="22">could</dependent>
          </dep>
          <dep type="auxpass">
            <governor idx="24">started</governor>
            <dependent idx="23">be</dependent>
          </dep>
          <dep type="advcl">
            <governor idx="3">planned</governor>
            <dependent idx="24">started</dependent>
          </dep>
          <dep type="prep_before">
            <governor idx="24">started</governor>
            <dependent idx="26">1996</dependent>
          </dep>
          <dep type="nsubj">
            <governor idx="29">said</governor>
            <dependent idx="28">Zainal</dependent>
          </dep>
        </dependencies>
        <dependencies type="collapsed-ccprocessed-dependencies">
          <dep type="root">
            <governor idx="0">ROOT</governor>
            <dependent idx="29">said</dependent>
          </dep>
          <dep type="nsubj">
            <governor idx="3">planned</governor>
            <dependent idx="1">Malaysia</dependent>
          </dep>
          <dep type="advmod">
            <governor idx="3">planned</governor>
            <dependent idx="2">originally</dependent>
          </dep>
          <dep type="ccomp">
            <governor idx="29">said</governor>
            <dependent idx="3">planned</dependent>
          </dep>
          <dep type="aux">
            <governor idx="5">export</governor>
            <dependent idx="4">to</dependent>
          </dep>
          <dep type="xcomp">
            <governor idx="3">planned</governor>
            <dependent idx="5">export</dependent>
          </dep>
          <dep type="dobj">
            <governor idx="5">export</governor>
            <dependent idx="6">electricity</dependent>
          </dep>
          <dep type="vmod">
            <governor idx="6">electricity</governor>
            <dependent idx="7">generated</dependent>
          </dep>
          <dep type="det">
            <governor idx="10">project</governor>
            <dependent idx="9">the</dependent>
          </dep>
          <dep type="agent">
            <governor idx="7">generated</governor>
            <dependent idx="10">project</dependent>
          </dep>
          <dep type="prep_to">
            <governor idx="7">generated</governor>
            <dependent idx="12">Singapore</dependent>
          </dep>
          <dep type="prep_to">
            <governor idx="7">generated</governor>
            <dependent idx="14">Brunei</dependent>
          </dep>
          <dep type="conj_and">
            <governor idx="12">Singapore</governor>
            <dependent idx="14">Brunei</dependent>
          </dep>
          <dep type="prep_to">
            <governor idx="7">generated</governor>
            <dependent idx="16">Indonesia</dependent>
          </dep>
          <dep type="conj_and">
            <governor idx="12">Singapore</governor>
            <dependent idx="16">Indonesia</dependent>
          </dep>
          <dep type="agent">
            <governor idx="7">generated</governor>
            <dependent idx="18">2000</dependent>
          </dep>
          <dep type="mark">
            <governor idx="24">started</governor>
            <dependent idx="19">if</dependent>
          </dep>
          <dep type="det">
            <governor idx="21">project</governor>
            <dependent idx="20">the</dependent>
          </dep>
          <dep type="nsubjpass">
            <governor idx="24">started</governor>
            <dependent idx="21">project</dependent>
          </dep>
          <dep type="aux">
            <governor idx="24">started</governor>
            <dependent idx="22">could</dependent>
          </dep>
          <dep type="auxpass">
            <governor idx="24">started</governor>
            <dependent idx="23">be</dependent>
          </dep>
          <dep type="advcl">
            <governor idx="3">planned</governor>
            <dependent idx="24">started</dependent>
          </dep>
          <dep type="prep_before">
            <governor idx="24">started</governor>
            <dependent idx="26">1996</dependent>
          </dep>
          <dep type="nsubj">
            <governor idx="29">said</governor>
            <dependent idx="28">Zainal</dependent>
          </dep>
        </dependencies>
      </sentence>
      <sentence id="4">
        <tokens>
          <token id="1">
            <word>Energy</word>
            <lemma>Energy</lemma>
            <CharacterOffsetBegin>561</CharacterOffsetBegin>
            <CharacterOffsetEnd>567</CharacterOffsetEnd>
            <POS>NNP</POS>
          </token>
          <token id="2">
            <word>import</word>
            <lemma>import</lemma>
            <CharacterOffsetBegin>568</CharacterOffsetBegin>
            <CharacterOffsetEnd>574</CharacterOffsetEnd>
            <POS>NN</POS>
          </token>
          <token id="3">
            <word>is</word>
            <lemma>be</lemma>
            <CharacterOffsetBegin>575</CharacterOffsetBegin>
            <CharacterOffsetEnd>577</CharacterOffsetEnd>
            <POS>VBZ</POS>
          </token>
          <token id="4">
            <word>about</word>
            <lemma>about</lemma>
            <CharacterOffsetBegin>578</CharacterOffsetBegin>
            <CharacterOffsetEnd>583</CharacterOffsetEnd>
            <POS>IN</POS>
          </token>
          <token id="5">
            <word>three</word>
            <lemma>three</lemma>
            <CharacterOffsetBegin>584</CharacterOffsetBegin>
            <CharacterOffsetEnd>589</CharacterOffsetEnd>
            <POS>CD</POS>
          </token>
          <token id="6">
            <word>times</word>
            <lemma>time</lemma>
            <CharacterOffsetBegin>590</CharacterOffsetBegin>
            <CharacterOffsetEnd>595</CharacterOffsetEnd>
            <POS>NNS</POS>
          </token>
          <token id="7">
            <word>the</word>
            <lemma>the</lemma>
            <CharacterOffsetBegin>596</CharacterOffsetBegin>
            <CharacterOffsetEnd>599</CharacterOffsetEnd>
            <POS>DT</POS>
          </token>
          <token id="8">
            <word>primary</word>
            <lemma>primary</lemma>
            <CharacterOffsetBegin>600</CharacterOffsetBegin>
            <CharacterOffsetEnd>607</CharacterOffsetEnd>
            <POS>JJ</POS>
          </token>
          <token id="9">
            <word>energy</word>
            <lemma>energy</lemma>
            <CharacterOffsetBegin>608</CharacterOffsetBegin>
            <CharacterOffsetEnd>614</CharacterOffsetEnd>
            <POS>NN</POS>
          </token>
          <token id="10">
            <word>in</word>
            <lemma>in</lemma>
            <CharacterOffsetBegin>615</CharacterOffsetBegin>
            <CharacterOffsetEnd>617</CharacterOffsetEnd>
            <POS>IN</POS>
          </token>
          <token id="11">
            <word>Singapore</word>
            <lemma>Singapore</lemma>
            <CharacterOffsetBegin>618</CharacterOffsetBegin>
            <CharacterOffsetEnd>627</CharacterOffsetEnd>
            <POS>NNP</POS>
          </token>
          <token id="12">
            <word>.</word>
            <lemma>.</lemma>
            <CharacterOffsetBegin>627</CharacterOffsetBegin>
            <CharacterOffsetEnd>628</CharacterOffsetEnd>
            <POS>.</POS>
          </token>
        </tokens>
        <parse>(ROOT (S (NP (NNP Energy) (NN import)) (VP (VBZ is) (ADVP (IN about) (NP (CD three) (NNS times))) (NP (NP (DT the) (JJ primary) (NN energy)) (PP (IN in) (NP (NNP Singapore))))) (. .))) </parse>
        <dependencies type="basic-dependencies">
          <dep type="root">
            <governor idx="0">ROOT</governor>
            <dependent idx="9">energy</dependent>
          </dep>
          <dep type="nn">
            <governor idx="2">import</governor>
            <dependent idx="1">Energy</dependent>
          </dep>
          <dep type="nsubj">
            <governor idx="9">energy</governor>
            <dependent idx="2">import</dependent>
          </dep>
          <dep type="cop">
            <governor idx="9">energy</governor>
            <dependent idx="3">is</dependent>
          </dep>
          <dep type="advmod">
            <governor idx="9">energy</governor>
            <dependent idx="4">about</dependent>
          </dep>
          <dep type="num">
            <governor idx="6">times</governor>
            <dependent idx="5">three</dependent>
          </dep>
          <dep type="pobj">
            <governor idx="4">about</governor>
            <dependent idx="6">times</dependent>
          </dep>
          <dep type="det">
            <governor idx="9">energy</governor>
            <dependent idx="7">the</dependent>
          </dep>
          <dep type="amod">
            <governor idx="9">energy</governor>
            <dependent idx="8">primary</dependent>
          </dep>
          <dep type="prep">
            <governor idx="9">energy</governor>
            <dependent idx="10">in</dependent>
          </dep>
          <dep type="pobj">
            <governor idx="10">in</governor>
            <dependent idx="11">Singapore</dependent>
          </dep>
        </dependencies>
        <dependencies type="collapsed-dependencies">
          <dep type="root">
            <governor idx="0">ROOT</governor>
            <dependent idx="9">energy</dependent>
          </dep>
          <dep type="nn">
            <governor idx="2">import</governor>
            <dependent idx="1">Energy</dependent>
          </dep>
          <dep type="nsubj">
            <governor idx="9">energy</governor>
            <dependent idx="2">import</dependent>
          </dep>
          <dep type="cop">
            <governor idx="9">energy</governor>
            <dependent idx="3">is</dependent>
          </dep>
          <dep type="advmod">
            <governor idx="9">energy</governor>
            <dependent idx="4">about</dependent>
          </dep>
          <dep type="num">
            <governor idx="6">times</governor>
            <dependent idx="5">three</dependent>
          </dep>
          <dep type="pobj">
            <governor idx="4">about</governor>
            <dependent idx="6">times</dependent>
          </dep>
          <dep type="det">
            <governor idx="9">energy</governor>
            <dependent idx="7">the</dependent>
          </dep>
          <dep type="amod">
            <governor idx="9">energy</governor>
            <dependent idx="8">primary</dependent>
          </dep>
          <dep type="prep_in">
            <governor idx="9">energy</governor>
            <dependent idx="11">Singapore</dependent>
          </dep>
        </dependencies>
        <dependencies type="collapsed-ccprocessed-dependencies">
          <dep type="root">
            <governor idx="0">ROOT</governor>
            <dependent idx="9">energy</dependent>
          </dep>
          <dep type="nn">
            <governor idx="2">import</governor>
            <dependent idx="1">Energy</dependent>
          </dep>
          <dep type="nsubj">
            <governor idx="9">energy</governor>
            <dependent idx="2">import</dependent>
          </dep>
          <dep type="cop">
            <governor idx="9">energy</governor>
            <dependent idx="3">is</dependent>
          </dep>
          <dep type="advmod">
            <governor idx="9">energy</governor>
            <dependent idx="4">about</dependent>
          </dep>
          <dep type="num">
            <governor idx="6">times</governor>
            <dependent idx="5">three</dependent>
          </dep>
          <dep type="pobj">
            <governor idx="4">about</governor>
            <dependent idx="6">times</dependent>
          </dep>
          <dep type="det">
            <governor idx="9">energy</governor>
            <dependent idx="7">the</dependent>
          </dep>
          <dep type="amod">
            <governor idx="9">energy</governor>
            <dependent idx="8">primary</dependent>
          </dep>
          <dep type="prep_in">
            <governor idx="9">energy</governor>
            <dependent idx="11">Singapore</dependent>
          </dep>
        </dependencies>
      </sentence>
    </sentences>
  </document>
</root>
